Workbook

Sheet Assumption
A1: Assumption Sheet
A2: Figures in lakhs
A3: Particular/Years | B3: Comments | C3: 2021-22 A | D3: 2022-23 A | E3: 2023-24 A | F3: 2024-25 A | G3: 2025-26 E | H3: 2026-27 E | I3: 2027-28 E | J3: 2028-29 E
A5: Revenue Model
A7: YoY Growth in Online Sales | B7: Explicit- Company provides not just luxury products but also the luxury experience in the store. So company will target more on Store sales than online sales. | C7: - | D7: =('Revenue Model'!D9/'Revenue Model'!C9)-1 -> 1.1172038 | E7: =('Revenue Model'!E9/'Revenue Model'!D9)-1 -> 0.22603073 | F7: =('Revenue Model'!F9/'Revenue Model'!E9)-1 -> 0.78327994 | G7: 0.3 | H7: 0.3 | I7: 0.3 | J7: 0.3
A9: ='Revenue Model'!A12 -> Number of Stores | B9: Explicit -As per management Guidance they are going to open 20 new stores every year and will cross 100 stores by end of FY 2025-56 (Kept as Best Case Scenario) | C9: ='Revenue Model'!C12 -> 50 | D9: ='Revenue Model'!D12 -> 56 | E9: ='Revenue Model'!E12 -> 63 | F9: ='Revenue Model'!F12 -> 73 | G9: =CHOOSE('Scenario Analysis'!$B$7,'Scenario Analysis'!G8,'Scenario Analysis'!G9,'Scenario Analysis'!G10) -> 100 | H9: =CHOOSE('Scenario Analysis'!$B$7,'Scenario Analysis'!H8,'Scenario Analysis'!H9,'Scenario Analysis'!H10) -> 108 | I9: =CHOOSE('Scenario Analysis'!$B$7,'Scenario Analysis'!I8,'Scenario Analysis'!I9,'Scenario Analysis'!I10) -> 116 | J9: =CHOOSE('Scenario Analysis'!$B$7,'Scenario Analysis'!J8,'Scenario Analysis'!J9,'Scenario Analysis'!J10) -> 124
A10: Same Store Growth | B10: Explicit - Management Guidance SSG = 12% (Kept as best case ) | C10: - | D10: 0.3 | E10: 0.16 | F10: 0.174 | G10: =CHOOSE('Scenario Analysis'!$B$13,'Scenario Analysis'!G14,'Scenario Analysis'!G15,'Scenario Analysis'!G16) -> 0.1 | H10: =CHOOSE('Scenario Analysis'!$B$13,'Scenario Analysis'!H14,'Scenario Analysis'!H15,'Scenario Analysis'!H16) -> 0.1 | I10: =CHOOSE('Scenario Analysis'!$B$13,'Scenario Analysis'!I14,'Scenario Analysis'!I15,'Scenario Analysis'!I16) -> 0.1 | J10: =CHOOSE('Scenario Analysis'!$B$13,'Scenario Analysis'!J14,'Scenario Analysis'!J15,'Scenario Analysis'!J16) -> 0.1
A11: Discount(In%) in Revenue of Exisiting store and New store (Age between 1 and 2 Year) | B11: Explicit | C11: - | D11: - | E11: - | F11: - | G11: =CHOOSE('Scenario Analysis'!$B$19,'Scenario Analysis'!G20,'Scenario Analysis'!G21,'Scenario Analysis'!G22) -> 0.6 | H11: =CHOOSE('Scenario Analysis'!$B$19,'Scenario Analysis'!H20,'Scenario Analysis'!H21,'Scenario Analysis'!H22) -> 0.6 | I11: =CHOOSE('Scenario Analysis'!$B$19,'Scenario Analysis'!I20,'Scenario Analysis'!I21,'Scenario Analysis'!I22) -> 0.6 | J11: =CHOOSE('Scenario Analysis'!$B$19,'Scenario Analysis'!J20,'Scenario Analysis'!J21,'Scenario Analysis'!J22) -> 0.6
A12: Discount(In%) in Revenue of Exisiting store and New store (Age between 1 and 2 Year) | B12: Explicit- They are targeting Teir-II cities so first year sales will be slower than usual. | C12: - | D12: - | E12: - | F12: - | G12: =CHOOSE('Scenario Analysis'!$B$24,'Scenario Analysis'!G25,'Scenario Analysis'!G26,'Scenario Analysis'!G27) -> 0.8 | H12: =CHOOSE('Scenario Analysis'!$B$24,'Scenario Analysis'!H25,'Scenario Analysis'!H26,'Scenario Analysis'!H27) -> 0.8 | I12: =CHOOSE('Scenario Analysis'!$B$24,'Scenario Analysis'!I25,'Scenario Analysis'!I26,'Scenario Analysis'!I27) -> 0.8 | J12: =CHOOSE('Scenario Analysis'!$B$24,'Scenario Analysis'!J25,'Scenario Analysis'!J26,'Scenario Analysis'!J27) -> 0.8
A15: Cost Model
A16: ='Cost Model'!A7 -> COGS/Revenue from operations | B16: Explicit - 2026 Because of EFTA Trade, 2027 will have some impact due to war situation and then remaining years COGS will normalize | C16: ='Cost Model'!C7 -> 0.71217046 | D16: ='Cost Model'!D7 -> 0.6903762 | E16: ='Cost Model'!E7 -> 0.69906509 | F16: ='Cost Model'!F7 -> 0.7004301 | G16: 0.69 | H16: 0.72 | I16: 0.7 | J16: 0.7
A18: ='Cost Model'!A13 -> Number of Board of Director | B18: Constant | C18: - | D18: ='Cost Model'!D13 -> 12 | E18: ='Cost Model'!E13 -> 10 | F18: ='Cost Model'!F13 -> 3 | G18: 3 | H18: 3 | I18: 3 | J18: 3
A19: ='Cost Model'!A14 -> Number of Key Managerial Personnel | B19: Constant | C19: - | D19: ='Cost Model'!D14 -> 3 | E19: ='Cost Model'!E14 -> 5 | F19: ='Cost Model'!F14 -> 2 | G19: 2 | H19: 2 | I19: 2 | J19: 2
A20: ='Cost Model'!A22 -> Employee per store | B20: Explicit | C20: - | D20: ='Cost Model'!D22 -> 9.4107143 | E20: ='Cost Model'!E22 -> 9.7936508 | F20: ='Cost Model'!F22 -> 10.616438 | G20: 11 | H20: 11 | I20: 11 | J20: 11
A21: Median Increase in the salary of BOD(in %) | B21: Explicit | G21: 0.02 | H21: 0.02 | I21: 0.02 | J21: 0.02
A22: Median Increase in the salary of KMP(in %) | B22: As per the Company Policy | C22: - | G22: 0.23 | H22: 0.23 | I22: 0.23 | J22: 0.23
A23: Median Increase in the salary of Employee other than BOD & KMP(in %) | B23: As per the Company Policy | C23: - | G23: 0.1063 | H23: 0.1063 | I23: 0.1063 | J23: 0.1063
A25: ='Cost Model'!A27 -> Advertisement and sales promotion expense/Revenue from operations | B25: Explicit- on the hgiher side as company is introducing products specifically made for india and also considering intial growth phase of brands like Rimowa luggage and Messika Jewellery | C25: ='Cost Model'!C27 -> 0.038547771 | D25: ='Cost Model'!D27 -> 0.034030125 | E25: ='Cost Model'!E27 -> 0.021022889 | F25: ='Cost Model'!F27 -> 0.019442612 | G25: 0.04 | H25: 0.03 | I25: 0.02 | J25: 0.02
A27: ='Cost Model'!A31 -> Other Expenses/Revenue | B27: Explicit | C27: ='Cost Model'!C31 -> 0.059970167 | D27: ='Cost Model'!D31 -> 0.063690873 | E27: ='Cost Model'!E31 -> 0.057609364 | F27: ='Cost Model'!F31 -> 0.060089143 | G27: 0.06 | H27: 0.06 | I27: 0.06 | J27: 0.06
A29: ='Cost Model'!A35 -> Effective Tax Rate | B29: Constant Average | C29: ='Cost Model'!C35 -> 0.25813379 | D29: ='Cost Model'!D35 -> 0.25259276 | E29: ='Cost Model'!E35 -> 0.25170309 | F29: ='Cost Model'!F35 -> 0.25971449 | G29: =AVERAGE($C$29:$F$29) -> 0.25553603 | H29: =AVERAGE($C$29:$F$29) -> 0.25553603 | I29: =AVERAGE($C$29:$F$29) -> 0.25553603 | J29: =AVERAGE($C$29:$F$29) -> 0.25553603
A31: =IS!A20 -> Dividend Paid | B31: Explicit- Company is in the growing phase and will reinvest all the profits | C31: =IS!C20 -> 0 | D31: =IS!D20 -> 0 | E31: =IS!E20 -> 0 | F31: =IS!F20 -> 0 | G31: 0 | H31: 0 | I31: 0 | J31: 0
A33: Capex Schedule
A35: Leasehold Improvements
A36: ='Capex Schedule'!A18 -> Total Useful Life | C36: ='Capex Schedule'!C18 -> 7.699002 | D36: ='Capex Schedule'!D18 -> 8.1836857 | E36: ='Capex Schedule'!E18 -> 6.6623899 | F36: ='Capex Schedule'!F18 -> 7.4476267 | G36: 7 | H36: 7 | I36: 7 | J36: 7
A37: ='Capex Schedule'!A22 -> Capex/Number of new Store Opened | C37: ='Capex Schedule'!C22 -> 80.883333 | D37: ='Capex Schedule'!D22 -> 133.34714 | E37: ='Capex Schedule'!E22 -> 102.176 | F37: ='Capex Schedule'!F22 -> 74.350741 | G37: 74.35 | H37: 74.35 | I37: 74.35 | J37: 74.35
A39: Plant and Equiment
A40: ='Capex Schedule'!A26 -> Add:Capex | B40: Constant | C40: ='Capex Schedule'!C26 -> 3.96 | D40: ='Capex Schedule'!D26 -> 53.6 | E40: ='Capex Schedule'!E26 -> 25.53 | F40: ='Capex Schedule'!F26 -> 266.33 | G40: 0 | H40: 0 | I40: 0 | J40: 0
A41: ='Capex Schedule'!A37 -> Total Useful Life | B41: Constant | C41: ='Capex Schedule'!C37 -> 17.87304 | D41: ='Capex Schedule'!D37 -> 17.526561 | E41: ='Capex Schedule'!E37 -> 14.555274 | F41: 13.802645 | G41: 13.802645 | H41: 13.802645 | I41: 13.802645 | J41: 13.802645
A43: Furniture and fittings
A44: ='Capex Schedule'!A56 -> Total Useful Life | B44: Explicit | C44: ='Capex Schedule'!C56 -> 12.104183 | D44: ='Capex Schedule'!D56 -> 10.6375 | E44: ='Capex Schedule'!E56 -> 9.5425381 | F44: ='Capex Schedule'!F56 -> 9.6936156 | G44: 10 | H44: 10 | I44: 10 | J44: 10
A45: ='Capex Schedule'!A60 -> Capex/Number of new store | B45: Explicit- Capex to open new bouqtic store in Tier II cities will be less as compared to Tier I city | C45: ='Capex Schedule'!C60 -> 77.288333 | D45: ='Capex Schedule'!D60 -> 104.40429 | E45: ='Capex Schedule'!E60 -> 101.154 | F45: ='Capex Schedule'!F60 -> 76.613333 | G45: 70 | H45: 70 | I45: 70 | J45: 70
A47: Office Equiments
A48: ='Capex Schedule'!A75 -> Total Useful Life | B48: Explicit | C48: ='Capex Schedule'!C75 -> 6.0814266 | D48: ='Capex Schedule'!D75 -> 4.9928938 | E48: ='Capex Schedule'!E75 -> 4.757856 | F48: ='Capex Schedule'!F75 -> 5.419905 | G48: 5 | H48: 5 | I48: 5 | J48: 5
A49: ='Capex Schedule'!A79 -> Opening Gross Block/Revenue | B49: Explicit | C49: ='Capex Schedule'!C79 -> 0.0041705664 | D49: ='Capex Schedule'!D79 -> 0.005730256 | E49: ='Capex Schedule'!E79 -> 0.0055562001 | F49: ='Capex Schedule'!F79 -> 0.0062056822 | G49: ='Capex Schedule'!G79 -> 0.0063382289 | H49: =G49-$C$50 -> 0.0058382289 | I49: =H49-$C$50 -> 0.0053382289 | J49: =I49-$C$50 -> 0.0048382289
A50: Opening Gross Block/Revenue Marginal Decrease- | B50: Explicit- To give benefit of economies of scale | C50: 0.0005
A52: Vechile
A53: ='Capex Schedule'!A95 -> Total Useful Life | B53: Explicit | C53: ='Capex Schedule'!C95 -> 10.201013 | D53: ='Capex Schedule'!D95 -> 11.383628 | E53: ='Capex Schedule'!E95 -> 7.0870635 | F53: ='Capex Schedule'!F95 -> 10.260632 | G53: 10 | H53: 10 | I53: 10 | J53: 10
A54: ='Capex Schedule'!A99 -> Capex/Number of new store | B54: Constant Average | C54: ='Capex Schedule'!C99 -> 33.671667 | D54: ='Capex Schedule'!D99 -> 86.987143 | E54: ='Capex Schedule'!E99 -> 113.617 | F54: ='Capex Schedule'!F99 -> 27.484815 | G54: =AVERAGE($C$54:$F$54) -> 65.440156 | H54: =AVERAGE($C$54:$F$54) -> 65.440156 | I54: =AVERAGE($C$54:$F$54) -> 65.440156 | J54: =AVERAGE($C$54:$F$54) -> 65.440156
A56: Lease Schedule
A58: Right of use asset
A59: ='Lease Schedule '!A15 -> Net Addition to ROU per newly opened store | B59: Explicit- Company is targeting Tier II cities to open new shop so rental per new store will be less than before but also considering a incremental increase in rent accounting for inflation etc | C59: ='Lease Schedule '!C15 -> 582.87667 | D59: ='Lease Schedule '!D15 -> 533.47714 | E59: ='Lease Schedule '!E15 -> 562.748 | F59: ='Lease Schedule '!F15 -> 694.68296 | G59: 550 | H59: =G59*(1+2%) -> 561 | I59: =H59*(1+2%) -> 572.22 | J59: =I59*(1+2%) -> 583.6644
A60: ='Lease Schedule '!A17 -> Average Remaining life of the lease | B60: Explicit | C60: ='Lease Schedule '!C17 -> 3.3014235 | D60: ='Lease Schedule '!D17 -> 3.5940285 | E60: ='Lease Schedule '!E17 -> 3.014737 | F60: ='Lease Schedule '!F17 -> 2.7667902 | G60: 4 | H60: 4 | I60: 4 | J60: 4
A62: Lease Liabilities
A63: Current Lease Liability/Total lease Liabilty | B63: Constant | C63: ='Lease Schedule '!C31/'Lease Schedule '!C30 -> 0.21973168 | D63: ='Lease Schedule '!D31/'Lease Schedule '!D30 -> 0.20905127 | E63: ='Lease Schedule '!E31/'Lease Schedule '!E30 -> 0.1974579 | F63: ='Lease Schedule '!F31/'Lease Schedule '!F30 -> 0.1457479 | G63: 0.15 | H63: 0.15 | I63: 0.15 | J63: 0.15
A64: ='Lease Schedule '!A35 -> Effective Interest Rate | B64: Explicit | C64: ='Lease Schedule '!C35 -> 0.11574863 | D64: ='Lease Schedule '!D35 -> 0.11317497 | E64: ='Lease Schedule '!E35 -> 0.13406247 | F64: ='Lease Schedule '!F35 -> 0.18512261 | G64: 0.1025 | H64: 0.1025 | I64: 0.1025 | J64: 0.1025
A67: Debt Schedule
A68: ='Debt Schedule '!A23 -> Effective Interest Rate on Borrowing | B68: Explicit- as per the average rate. Capex loan =10.5% and Working Capital loan =14% | C68: - | D68: ='Debt Schedule '!D23 -> 0.040917299 | E68: ='Debt Schedule '!E23 -> 0.10542915 | F68: ='Debt Schedule '!F23 -> 0.14280809 | G68: 0.1225 | H68: 0.1225 | I68: 0.1225 | J68: 0.1225
A70: WC Schedule
A71: ='WC Schedule'!A10 -> Number of Days in Inventory | B71: Explicit- New stores in Tier II cities will take more time to clear stock initally but will eventually reduce due to brand recognition | C71: - | D71: ='WC Schedule'!D10 -> 227.87849 | E71: ='WC Schedule'!E10 -> 229.80611 | F71: ='WC Schedule'!F10 -> 246.7553 | G71: 220 | H71: 200 | I71: 190 | J71: 180
A72: ='WC Schedule'!A15 -> Number of Days in Trade Receivable | B72: Explicit- New stores in Tier II cities will take more time | C72: - | D72: ='WC Schedule'!D15 -> 2.8594225 | E72: ='WC Schedule'!E15 -> 5.6894779 | F72: ='WC Schedule'!F15 -> 5.3248428 | G72: 5 | H72: 5 | I72: 5 | J72: 5
A73: ='WC Schedule'!A21 -> Number of days of Trade Payable | B73: Explict - From numbers it seems like they get a credit period of 2 months | C73: - | D73: ='WC Schedule'!D21 -> 55.575528 | E73: ='WC Schedule'!E21 -> 43.885135 | F73: ='WC Schedule'!F21 -> 31.463406 | G73: 45 | H73: 50 | I73: 55 | J73: 60
A76: Valuation Sheet
A77: =Valuation!A39 -> PS/G Ratio | B77: =CHOOSE('Scenario Analysis'!B29,'Scenario Analysis'!G30,'Scenario Analysis'!G31,'Scenario Analysis'!G32) -> 0.15
A78: =Valuation!A46 -> PEG Ratio | B78: =CHOOSE('Scenario Analysis'!B34,'Scenario Analysis'!G35,'Scenario Analysis'!G36,'Scenario Analysis'!G37) -> 1.15
A80: =Valuation!A63 -> Forecasted Terminal PE | B80: =CHOOSE('Scenario Analysis'!$B$39,'Scenario Analysis'!G40,'Scenario Analysis'!G41,'Scenario Analysis'!G42) -> 40
A82: Risk free Rate | B82: 0.0603
A83: Equity Risk Premium | B83: 0.0708
A84: Beta | B84: 0.75
A85: =Valuation!A67 -> Cost of equity | B85: =CHOOSE('Scenario Analysis'!B44,'Scenario Analysis'!G45,'Scenario Analysis'!G46,'Scenario Analysis'!G47) -> 0.25

Sheet Valuation
A1: Valuation
A2: Figures in lakhs
A3: Particular/Years | B3: Comments
A5: Comparable Company Analysis
C6: Ethos Ltd. | D6: P N Gadgil jewellers | E6: Metro Brands | F6: Trent Ltd | G6: Avenue Supermart | H6: Vedant Fashion Ltd
A7: Market Capitalisation (In Cr.) | C7: 5416 | D7: 7478 | E7: 24921 | F7: 1,27,842.00 | G7: 246107 | H7: 8319
A8: Net Sales (TTM) | C8: 1510 | D8: 8783 | E8: 2733 | F8: 19263 | G8: 66009 | H8: 1403
A9: Net Sales 2025 | C9: 1252 | D9: 7586 | E9: 2507 | F9: 17135 | G9: 59358 | H9: 1386
A10: EBIDTA | C10: 197 | D10: 337 | E10: 759 | F10: 2820 | G10: 4495 | H10: 643
A11: CFO | C11: -20 | D11: -675 | E11: 698 | F11: 1661 | G11: 2463 | H11: 389
A12: CFO/EBIDTA Translation | C12: -0.10152284 | D12: -0.088979699 | E12: 0.91963109 | F12: 0.58900709 | G12: 0.54794216 | H12: 0.60497667
A13: CFO before WC Adj | C13: 192 | D13: 278 | E13: 641 | F13: 2229 | G13: 3576 | H13: 520
A14: CFO before WC Adj/EBIDTA | C14: 0.97461929 | D14: 0.82492582 | E14: 0.84453228 | F14: 0.79042553 | G14: 0.79555061 | H14: 0.80870918
A16: Gross Profit Margin | C16: 0.29 | D16: 0.0907 | E16: 0.5332 | F16: 0.39 | G16: 0.11 | H16: 0.6705
A17: Operating Profit Margin | C17: 0.16 | D17: 0.04 | E17: 0.3 | F17: 0.16 | G17: 0.08 | H17: 0.46
A18: Net Profit Margin | C18: 0.076677316 | D18: 0.028737147 | E18: 0.14120463 | F18: 0.089524365 | G18: 0.049340187 | H18: 0.27994228
A20: Number of Days in Inventory | C20: 247 | D20: 104 | E20: 228 | F20: 77 | G20: 36 | H20: 210
A21: Return on Capital Employed | C21: 0.138 | D21: 0.194 | E21: 0.194 | F21: 0.307 | G21: 0.18 | H21: 0.259
... A30: PSG Ratio | C30: 0.16272727 | D30: 0.034 | E30: 0.65142857 | F30: 0.17473684 | G30: 0.19631579 | H30: 0.65888889
A33: Relative Valuation
A34: =A7 -> Market Capitalisation (In Cr.) | B34: =C7 -> 5416
A35: Number of Share Outstanding (Ending 2025) | B35: 244.80443
A36: 1 Year Trailing Sales (2025-26) | B36: =IS!G4 -> 185499.77
A37: Price to Sales (Trailing ) | B37: =B38*B39*100 -> 2.7763557
A38: Estimated CAGR for next 4 years | B38: =(IS!J4/IS!G4)^0.25-1 -> 0.18509038
A39: PS/G Ratio | B39: =Assumption!B77 -> 0.15
A40: Valuation Based on PS Multiple | B40: =B36*B37 -> 515013.34
A41: Valuation Per Share Base on PS Multiple | B41: =B40/B35 -> 2103.7746
A44: 1 Year Trailing PAT (2025-26) | B44: =IS!G19 -> 16063.232
A45: Estimated CAGR for next 4 years | B45: =(IS!J19/IS!G19)^0.25-1 -> 0.28405036
A46: PEG Ratio | B46: =Assumption!B78 -> 1.15
A47: PE Multiple | B47: =B45*B46*100 -> 32.665791
A48: Valution Based on PE Multiple | B48: =B47*B44 -> 524718.2
A49: Valution Per Share Based on PE Multiple | B49: =B48/B35 -> 2143.4179
A51: Absolute Valuation
A53: Discounted Cash Flow (DCF)
A55: Dates | H55: =DATE(2027,3,31) -> 46477 | I55: =DATE(2028,3,31) -> 46843 | J55: =DATE(2029,3,31) -> 47208
A56: =CF!A36 -> Cash flow from operations | H56: =CF!H36 -> 25561.865 | I56: =CF!I36 -> 46538.224 | J56: =CF!J36 -> 58893.852
A57: =CF!A40 -> Acquisition of property, plant and equipment | H57: =CF!H40 -> -1847.5359 | I57: =CF!I40 -> -1885.3135 | J57: =CF!J40 -> -4402.7954
A58: FCFF | H58: =SUM(H56:H57) -> 23714.329 | I58: =SUM(I56:I57) -> 44652.911 | J58: =SUM(J56:J57) -> 54491.056
A59: ="Less: " & CF!A57 -> Less: Interest expense paid | H59: =CF!H57 -> -2783.3025 | I59: =CF!I57 -> -2650.9586 | J59: =CF!J57 -> -2556.2267
A60: ="Less: " & CF!A55 -> Less: Payment of principal portion of lease liabilities | H60: =CF!H55 -> -5779.1598 | I60: =CF!I55 -> -5501.974 | J60: =CF!J55 -> -5303.564
A61: FCFE | H61: =SUM(H58:H60) -> 15151.867 | I61: =SUM(I58:I60) -> 36499.978 | J61: =SUM(J58:J60) -> 46631.266
A62: Forecasted PAT for terminal year | B62: =IS!J19 -> 43667.786
A63: Forecasted Terminal PE | B63: =Assumption!B80 -> 40
A64: Forecasted Terminal Value | B64: =B62*B63 -> 1746711.4 | H64: 0 | I64: 0 | J64: =B64 -> 1746711.4
A65: Total Cash flow | H65: =H61+H64 -> 15151.867 | I65: =I61+I64 -> 36499.978 | J65: =J61+J64 -> 1793342.7
A67: Cost of equity | B67: =Assumption!B85 -> 0.25
A69: Valution Based on FCFE | B69: =XNPV(B67,H65:J65,H55:J55) -> 1191371.9
A70: Valuation Per Share based on FCFE | B70: =B69/B35 -> 4866.6271
A72: Contribution of FCFE to Valuation | B72: =XNPV(B67,H61:J61,H55:J55) -> 74159.773
A73: Contribution of terminal value to Valuation | B73: =XNPV(B67,H64:J64,H55:J55) -> 1117212.1
A76: % of Contribution of FCFE to Valuation | B76: =B72/B69 -> 0.062247376
A77: % of Contribution of terminal value to Valuation | B77: =B73/B69 -> 0.93775262
A81: Average Valuation Per Share | B81: =AVERAGE(B41,B49,B70) -> 3037.9399

Sheet Scenario Analysis
A1: Scenario Analysis
A2: Figures in lakhs
A3: Particular/Years | B3: Comments | C3: 2021-22 A | D3: 2022-23 A | E3: 2023-24 A | F3: 2024-25 A | G3: 2025-26 E | H3: 2026-27 E | I3: 2027-28 E | J3: 2028-29 E
A5: Valuation Per Share | B5: =Valuation!B81 -> 3037.9399
A7: Number of Stores | B7: 2
A8: Best Case Scenario | B8: 1 | C8: 50 | D8: 56 | E8: 63 | F8: 73 | G8: 100 | H8: 120 | I8: 140 | J8: 160
A9: Base Case Scenario | B9: 2 | C9: 50 | D9: 56 | E9: 63 | F9: 73 | G9: 100 | H9: =G9+8 -> 108 | I9: =H9+8 -> 116 | J9: =I9+8 -> 124
A10: Worst Case Scenario | B10: 3 | C10: 50 | D10: 56 | E10: 63 | F10: 73 | G10: =F10+10 -> 83 | H10: =G10+5 -> 88 | I10: =H10+5 -> 93 | J10: =I10+5 -> 98
A13: Same Store Growth | B13: 2
A14: Best Case Scenario | B14: 1 | C14: - | D14: 0.3 | E14: 0.16 | F14: 0.174 | G14: 0.12 | H14: 0.12 | I14: 0.12 | J14: 0.12
A15: Base Case Scenario | B15: 2 | C15: - | D15: 0.3 | E15: 0.16 | F15: 0.174 | G15: 0.1 | H15: 0.1 | I15: 0.1 | J15: 0.1
A16: Worst Case Scenario | B16: 3 | C16: - | D16: 0.3 | E16: 0.16 | F16: 0.174 | G16: 0.08 | H16: 0.08 | I16: 0.08 | J16: 0.08
A19: Discount(In%) in Revenue of Exisiting store and New store (Age between 1 and 2 Year) | B19: 2
A20: Best Case Scenario | B20: 1 | C20: - | D20: - | E20: - | F20: - | G20: 0.4 | H20: 0.4 | I20: 0.4 | J20: 0.4
A21: Base Case Scenario | B21: 2 | C21: - | D21: - | E21: - | F21: - | G21: 0.6 | H21: 0.6 | I21: 0.6 | J21: 0.6
A22: Worst Case Scenario | B22: 3 | C22: - | D22: - | E22: - | F22: - | G22: 0.8 | H22: 0.8 | I22: 0.8 | J22: 0.8
A24: Discount(In%) in Revenue of Exisiting store and New store (Age between 1 and 2 Year) | B24: 2
A25: Best Case Scenario | B25: 1 | C25: - | D25: - | E25: - | F25: - | G25: 0.7 | H25: 0.7 | I25: 0.7 | J25: 0.7
A26: Base Case Scenario | B26: 2 | C26: - | D26: - | E26: - | F26: - | G26: 0.8 | H26: 0.8 | I26: 0.8 | J26: 0.8
A27: Worst Case Scenario | B27: 3 | C27: - | D27: - | E27: - | F27: - | G27: 0.9 | H27: 0.9 | I27: 0.9 | J27: 0.9
A29: PS/G Ratio | B29: 3
A30: Best Case Scenario | B30: 1 | G30: 0.4
A31: Base Case Scenario | B31: 2 | G31: 0.3
A32: Worst Case Scenario | B32: 3 | G32: 0.15
A34: PEG Ratio | B34: 2
A35: Best Case Scenario | B35: 1 | G35: 3
A36: Base Case Scenario | B36: 2 | G36: 1.15
A37: Worst Case Scenario | B37: 3 | G37: 0.2
A39: Forecasted Terminal PE | B39: 3
A40: Best Case Scenario | B40: 1 | G40: 100.07
A41: Base Case Scenario | B41: 2 | G41: =AVERAGE(G40,G42) -> 70.035
A42: Worst Case Scenario | B42: 3 | G42: 40
A44: Cost of equity | B44: 3
A45: Best Case Scenario | B45: 1 | G45: 0.1134
A46: Base Case Scenario | B46: 2 | G46: 0.2
A47: Worst Case Scenario | B47: 3 | G47: 0.25

Sheet BS
A1: Balance Sheet
A2: Figures in lakhs
A3: Particular/Years | B3: Comments | C3: 2021-22 A | D3: 2022-23 A | E3: 2023-24 A | F3: 2024-25 A | G3: 2025-26 E | H3: 2026-27 E | I3: 2027-28 E | J3: 2028-29 E
A4: ASSETS
A5: Non-current assets
A6: Property, plant and equipment | B6: Capex Schdeule | C6: 3726.02 | D6: 5284.41 | E6: 6324.2 | F6: 9776.71 | G6: ='Capex Schedule'!G114 -> 9863.8534 | H6: ='Capex Schedule'!H114 -> 9664.919 | I6: ='Capex Schedule'!I114 -> 9276.5957 | J6: ='Capex Schedule'!J114 -> 11171.032
A7: Capital work-in-progress | B7: Capex Schdeule | C7: 0 | D7: 401.45 | E7: 701.79 | F7: 3057.41 | G7: ='Capex Schedule'!G124 -> 3057.41 | H7: ='Capex Schedule'!H124 -> 3057.41 | I7: ='Capex Schedule'!I124 -> 3057.41 | J7: ='Capex Schedule'!J124 -> 3057.41
A8: Intangible assets | B8: Constant | C8: 66.3 | D8: 4070.65 | E8: 4111.13 | F8: 4297.73 | G8: 4297.73 | H8: 4297.73 | I8: 4297.73 | J8: 4297.73
A9: Right-of-use assets | B9: Lease Schedule | C9: 9159.13 | D9: 10345.04 | E9: 12541.03 | F9: 26045.04 | G9: ='Lease Schedule '!G10 -> 23933.78 | H9: ='Lease Schedule '!H10 -> 22438.335 | I9: ='Lease Schedule '!I10 -> 21406.511 | J9: ='Lease Schedule '!J10 -> 27728.171
A10: Intangible assets under development | B10: Constant | C10: 0 | D10: 0 | E10: 154.47 | F10: 3.5 | G10: 3.5 | H10: 3.5 | I10: 3.5 | J10: 3.5
A11: Investment in joint venture | B11: Constant | C11: 157.47 | D11: 207.15 | E11: 2401.14 | F11: 3444.76 | G11: 3444.76 | H11: 3444.76 | I11: 3444.76 | J11: 3444.76
A12: Investments | B12: Constant | C12: 0 | D12: 0 | E12: 134.92 | F12: 177.45 | G12: 177.45 | H12: 177.45 | I12: 177.45 | J12: 177.45
A13: Loans | B13: Constant | C13: 3.67 | D13: 5.67 | E13: 1.7 | F13: 0 | G13: 0 | H13: 0 | I13: 0 | J13: 0
A14: Other financial assets | B14: Constant | C14: 1106.96 | D14: 2452.01 | E14: 2816.99 | F14: 2762.94 | G14: 2762.94 | H14: 2762.94 | I14: 2762.94 | J14: 2762.94
A15: Non-current tax assets (net) | B15: Constant | C15: 188.32 | D15: 234.79 | E15: 209.58 | F15: 171.06 | G15: 171.06 | H15: 171.06 | I15: 171.06 | J15: 171.06
A16: Deferred tax assets (net) | B16: Constant | C16: 906.17 | D16: 860.62 | E16: 903.91 | F16: 941.52 | G16: 941.52 | H16: 941.52 | I16: 941.52 | J16: 941.52
A17: Other non-current assets | B17: Constant | C17: 1479.39 | D17: 255.24 | E17: 357.77 | F17: 1234.01 | G17: 1234.01 | H17: 1234.01 | I17: 1234.01 | J17: 1234.01
A18: Total Non Current Assets | C18: =SUM(C6:C17) -> 16793.43 | D18: =SUM(D6:D17) -> 24117.03 | E18: =SUM(E6:E17) -> 30658.63 | F18: =SUM(F6:F17) -> 51912.13 | G18: =SUM(G6:G17) -> 49888.013 | H18: =SUM(H6:H17) -> 48193.634 | I18: =SUM(I6:I17) -> 46773.487 | J18: =SUM(J6:J17) -> 54989.584
A19: Current Assets
A20: Inventories | B20: WC Schedule | C20: 24993.29 | D20: 33987.29 | E20: 43969.18 | F20: 59267.06 | G20: ='WC Schedule'!G8 -> 77147.576 | H20: ='WC Schedule'!H8 -> 94203.29 | I20: ='WC Schedule'!I8 -> 106707.12 | J20: ='WC Schedule'!J8 -> 126306.86
A21: Trade receivables | B21: WC Schedule | C21: 518.26 | D21: 617.74 | E21: 1557.19 | F21: 1825.95 | G21: ='WC Schedule'!G13 -> 1753.354 | H21: ='WC Schedule'!H13 -> 2355.0823 | I21: ='WC Schedule'!I13 -> 2808.0821 | J21: ='WC Schedule'!J13 -> 3508.5239
A22: Cash and cash equivalents | B22: CF | C22: 3768.32 | D22: 2788.87 | E22: 6057.91 | F22: 2848.01 | G22: =CF!G62 -> 10480.148 | H22: =CF!H62 -> 21179.519 | I22: =CF!I62 -> 48736.838 | J22: =CF!J62 -> 82809.188
A23: Other bank balances | B23: Constant | C23: 215.58 | D23: 20074.43 | E23: 28488.15 | F23: 19154.44 | G23: 19154.44 | H23: 19154.44 | I23: 19154.44 | J23: 19154.44
A24: Loans | B24: Debt Schedule | C24: 26.94 | D24: 25.28 | E24: 23.73 | F24: 4.68 | G24: 4.68 | H24: 4.68 | I24: 4.68 | J24: 4.68
A25: Other financial assets | B25: Constant | C25: 710.52 | D25: 1500.93 | E25: 2165 | F25: 1116.71 | G25: 1116.71 | H25: 1116.71 | I25: 1116.71 | J25: 1116.71
A26: Other current assets | B26: Constant | C26: 3409.35 | D26: 4858.06 | E26: 4144.31 | F26: 4835.52 | G26: 4835.52 | H26: 4835.52 | I26: 4835.52 | J26: 4835.52
A27: Total current assets | C27: =SUM(C20:C26) -> 33642.26 | D27: =SUM(D20:D26) -> 63852.6 | E27: =SUM(E20:E26) -> 86405.47 | F27: =SUM(F20:F26) -> 89052.37 | G27: =SUM(G20:G26) -> 114492.43 | H27: =SUM(H20:H26) -> 142849.24 | I27: =SUM(I20:I26) -> 183363.39 | J27: =SUM(J20:J26) -> 237735.92
A29: Total Assets | C29: =C18+C27 -> 50435.69 | D29: =D18+D27 -> 87969.63 | E29: =E18+E27 -> 117064.1 | F29: =F18+F27 -> 140964.5 | G29: =G18+G27 -> 164380.44 | H29: =H18+H27 -> 191042.88 | I29: =I18+I27 -> 230136.87 | J29: =J18+J27 -> 292725.51
A31: EQUITY AND LIABILITIES
A32: Equity
A33: Equity share capital | B33: Constant | C33: 1907.82 | D33: 2334.92 | E33: 2448.04 | F33: 2448.04 | G33: 2448.04 | H33: 2448.04 | I33: 2448.04 | J33: 2448.04
A34: Other equity | C34: 21260.67 | D34: 60814.72 | E34: 85948.65 | F34: 95771.65 | G34: =F34+IS!G21 -> 111834.88 | H34: =G34+IS!H21 -> 131885.89 | I34: =H34+IS!I21 -> 165018.28 | J34: =I34+IS!J21 -> 208686.07
A35: Total equity | C35: =SUM(C33:C34) -> 23168.49 | D35: =SUM(D33:D34) -> 63149.64 | E35: =SUM(E33:E34) -> 88396.69 | F35: =SUM(F33:F34) -> 98219.69 | G35: =SUM(G33:G34) -> 114282.92 | H35: =SUM(H33:H34) -> 134333.93 | I35: =SUM(I33:I34) -> 167466.32 | J35: =SUM(J33:J34) -> 211134.11
A36: Liabilities
A37: Non-current liabilities
A38: Borrowings | B38: Debt Schedule | C38: 2764.42 | D38: 711.77 | E38: 205.98 | F38: 12.55 | G38: ='Debt Schedule '!G15 -> 12.55 | H38: ='Debt Schedule '!H15 -> 12.55 | I38: ='Debt Schedule '!I15 -> 12.55 | J38: ='Debt Schedule '!J15 -> 12.55
A39: Lease liabilities | B39: Lease Schedule | C39: 7948.57 | D39: 8916.8 | E39: 11100.65 | F39: 24496.61 | G39: ='Lease Schedule '!G32 -> 22881.928 | H39: ='Lease Schedule '!H32 -> 21784.442 | I39: ='Lease Schedule '!I32 -> 20998.86 | J39: ='Lease Schedule '!J32 -> 26413.126
A40: Other financial liabilities | B40: Constant | C40: 66.9 | D40: 47.15 | E40: 34.59 | F40: 0 | G40: 0 | H40: 0 | I40: 0 | J40: 0
A41: Employee benefit obligations | B41: Constant | C41: 142.35 | D41: 192.35 | E41: 249.5 | F41: 288.3 | G41: 288.3 | H41: 288.3 | I41: 288.3 | J41: 288.3
A42: Total non-current liabilities | C42: =SUM(C38:C41) -> 10922.24 | D42: =SUM(D38:D41) -> 9868.07 | E42: =SUM(E38:E41) -> 11590.72 | F42: =SUM(F38:F41) -> 24797.46 | G42: =SUM(G38:G41) -> 23182.778 | H42: =SUM(H38:H41) -> 22085.292 | I42: =SUM(I38:I41) -> 21299.71 | J42: =SUM(J38:J41) -> 26713.976
A43: Current liabilities
A44: Borrowings | C44: 3177.81 | D44: 87.25 | E44: 463.87 | F44: 183.46 | G44: ='Debt Schedule '!G16 -> 183.46 | H44: ='Debt Schedule '!H16 -> 183.46 | I44: ='Debt Schedule '!I16 -> 183.46 | J44: ='Debt Schedule '!J16 -> 183.46
A45: Lease liabilities | B45: Lease Schedule | C45: 2238.4 | D45: 2356.75 | E45: 2731.21 | F45: 4179.48 | G45: ='Lease Schedule '!G31 -> 4037.9873 | H45: ='Lease Schedule '!H31 -> 3844.3133 | I45: ='Lease Schedule '!I31 -> 3705.6812 | J45: ='Lease Schedule '!J31 -> 4661.1398
A46: Trade payables | B46: Merged with Dues outstanding of of micro enterprises and small enterprises & others | C46: 8354.08 | D46: 9658.34 | E46: 9596.77 | F46: 8875.75 | G46: ='WC Schedule'!G18 -> 17984.633 | H46: ='WC Schedule'!H18 -> 25887.222 | I46: ='WC Schedule'!I18 -> 32773.041 | J46: ='WC Schedule'!J18 -> 45324.163
A47: Other financial liabilities | B47: Constant | C47: 952.64 | D47: 1058 | E47: 2359.1 | F47: 2285.67 | G47: 2285.67 | H47: 2285.67 | I47: 2285.67 | J47: 2285.67
A48: Other current liabilities | B48: Constant | C48: 1276.88 | D48: 1380.25 | E48: 1423.9 | F48: 1931.44 | G48: 1931.44 | H48: 1931.44 | I48: 1931.44 | J48: 1931.44
A49: Employee benefit obligations | B49: Constant | C49: 324.9 | D49: 390.56 | E49: 462.67 | F49: 477.27 | G49: 477.27 | H49: 477.27 | I49: 477.27 | J49: 477.27
A50: Current tax liabilities (net) | B50: Constant | C50: 20.25 | D50: 20.77 | E50: 39.18 | F50: 14.28 | G50: 14.28 | H50: 14.28 | I50: 14.28 | J50: 14.28
A51: Total current liabilities | C51: =SUM(C44:C50) -> 16344.96 | D51: =SUM(D44:D50) -> 14951.92 | E51: =SUM(E44:E50) -> 17076.7 | F51: =SUM(F44:F50) -> 17947.35 | G51: =SUM(G44:G50) -> 26914.74 | H51: =SUM(H44:H50) -> 34623.655 | I51: =SUM(I44:I50) -> 41370.842 | J51: =SUM(J44:J50) -> 54877.422
A52: Total liabilities | C52: =C42+C51 -> 27267.2 | D52: =D42+D51 -> 24819.99 | E52: =E42+E51 -> 28667.42 | F52: =F42+F51 -> 42744.81 | G52: =G42+G51 -> 50097.518 | H52: =H42+H51 -> 56708.947 | I52: =I42+I51 -> 62670.553 | J52: =J42+J51 -> 81591.398
A53: Total Equity and Liabilites | C53: =C35+C52 -> 50435.69 | D53: =D35+D52 -> 87969.63 | E53: =E35+E52 -> 117064.11 | F53: =F35+F52 -> 140964.5 | G53: =G35+G52 -> 164380.44 | H53: =H35+H52 -> 191042.88 | I53: =I35+I52 -> 230136.87 | J53: =J35+J52 -> 292725.51
G54: =G53=G29 -> TRUE | H54: =H53=H29 -> TRUE | I54: =I53=I29 -> TRUE | J54: =J53=J29 -> TRUE
G55: =G53-G29 -> 0 | H55: =H53-H29 -> 0 | I55: =I53-I29 -> 0 | J55: =J53-J29 -> 0
A58: -
A60: -

Sheet IS
A1: Income Statement
A2: Figures in lakhs
A3: Particular/Years | B3: Comments | C3: 2021-22 A | D3: 2022-23 A | E3: 2023-24 A | F3: 2024-25 A | G3: 2025-26 E | H3: 2026-27 E | I3: 2027-28 E | J3: 2028-29 E
A4: Revenue from operations | C4: 57728.37 | D4: 78853.37 | E4: 99899.21 | F4: 125162.71 | G4: ='Revenue Model'!G4 -> 185499.77 | H4: ='Revenue Model'!H4 -> 238779.17 | I4: ='Revenue Model'!I4 -> 292842.84 | J4: ='Revenue Model'!J4 -> 365888.92
A5: Cost of Goods Sold | B5: Merged with Purchase of stock-in-trade and Changes in inventory of stock-in-trade | C5: 41112.44 | D5: 54438.49 | E5: 69836.05 | F5: 87667.73 | G5: ='Cost Model'!G8 -> 127994.84 | H5: ='Cost Model'!H8 -> 171921 | I5: ='Cost Model'!I8 -> 204989.99 | J5: ='Cost Model'!J8 -> 256122.25
A6: Gross Profit | C6: =C4-C5 -> 16615.93 | D6: =D4-D5 -> 24414.88 | E6: =E4-E5 -> 30063.16 | F6: =F4-F5 -> 37494.98 | G6: =G4-G5 -> 57504.929 | H6: =H4-H5 -> 66858.169 | I6: =I4-I5 -> 87852.853 | J6: =J4-J5 -> 109766.68
A7: Employee benefits expense | C7: 4238.15 | D7: 5268.17 | E7: 7036.38 | F7: 8533.57 | G7: ='Cost Model'!G24 -> 8523.9653 | H7: ='Cost Model'!H24 -> 10051.324 | I7: ='Cost Model'!I24 -> 11816.193 | J7: ='Cost Model'!J24 -> 13852.648
A8: Advertisement and sales promotion expense | C8: 2225.3 | D8: 2683.39 | E8: 2100.17 | F8: 2433.49 | G8: ='Cost Model'!G28 -> 7419.9908 | H8: ='Cost Model'!H28 -> 7163.3752 | I8: ='Cost Model'!I28 -> 5856.8569 | J8: ='Cost Model'!J28 -> 7317.7785
A9: Other Expense | C9: 3461.98 | D9: 5022.24 | E9: 5755.13 | F9: 7520.92 | G9: ='Cost Model'!G32 -> 11129.986 | H9: ='Cost Model'!H32 -> 14326.75 | I9: ='Cost Model'!I32 -> 17570.571 | J9: ='Cost Model'!J32 -> 21953.335
A10: Earning Before Interest,Depreciation,Tax & Amortization | C10: =C6-SUM(C7:C9) -> 6690.5 | D10: =D6-SUM(D7:D9) -> 11441.08 | E10: =E6-SUM(E7:E9) -> 15171.48 | F10: =F6-SUM(F7:F9) -> 19007 | G10: =G6-SUM(G7:G9) -> 30430.986 | H10: =H6-SUM(H7:H9) -> 35316.719 | I10: =I6-SUM(I7:I9) -> 52609.233 | J10: =J6-SUM(J7:J9) -> 66642.915
A11: Depreciation and amortization expense | C11: 3150.86 | D11: 3463.09 | E11: 4867.46 | F11: 6300.31 | G11: ='Capex Schedule'!G109+'Lease Schedule '!G9 -> 8320.7453 | H11: ='Capex Schedule'!H109+'Lease Schedule '!H9 -> 8029.9153 | I11: ='Capex Schedule'!I109+'Lease Schedule '!I9 -> 7883.2206 | J11: ='Capex Schedule'!J109+'Lease Schedule '!J9 -> 7859.9866
A12: Earning Before Interest & Tax(EBIT) | C12: =C10-C11 -> 3539.64 | D12: =D10-D11 -> 7977.99 | E12: =E10-E11 -> 10304.02 | F12: =F10-F11 -> 12706.69 | G12: =G10-G11 -> 22110.241 | H12: =H10-H11 -> 27286.804 | I12: =I10-I11 -> 44726.012 | J12: =J10-J11 -> 58782.928
A13: Finance costs | C13: 1667.28 | D13: 1416.06 | E13: 1601.8 | F13: 1943.84 | G13: ='Debt Schedule '!G11 -> 2963.3104 | H13: ='Debt Schedule '!H11 -> 2783.3025 | I13: ='Debt Schedule '!I11 -> 2650.9586 | J13: ='Debt Schedule '!J11 -> 2556.2267
A14: Other income | C14: 1277.83 | D14: 1456.04 | E14: 2361.68 | F14: 2429.98 | G14: 2429.98 | H14: 2429.98 | I14: 2429.98 | J14: 2429.98
A15: Earnings Before Tax and Before Profir share of Joint Venture | C15: =C12-C13+C14 -> 3150.19 | D15: =D12-D13+D14 -> 8017.97 | E15: =E12-E13+E14 -> 11063.9 | F15: =F12-F13+F14 -> 13192.83 | G15: =G12-G13+G14 -> 21576.911 | H15: =H12-H13+H14 -> 26933.481 | I15: =I12-I13+I14 -> 44505.034 | J15: =J12-J13+J14 -> 58656.682
A16: Share of profit of joint venture (net of income tax) (IV) | C16: 2.4 | D16: 49.68 | E16: 67.31 | F16: -185.97 | G16: 0 | H16: 0 | I16: 0 | J16: 0
A17: Earning Before Tax (EBT) | C17: =C15+C16 -> 3152.59 | D17: =D15+D16 -> 8067.65 | E17: =E15+E16 -> 11131.21 | F17: =F15+F16 -> 13006.86 | G17: =G15+G16 -> 21576.911 | H17: =H15+H16 -> 26933.481 | I17: =I15+I16 -> 44505.034 | J17: =J15+J16 -> 58656.682
A18: Tax Expense | C18: 813.79 | D18: 2037.83 | E18: 2801.76 | F18: 3378.07 | G18: ='Cost Model'!G36 -> 5513.6782 | H18: ='Cost Model'!H36 -> 6882.4749 | I18: ='Cost Model'!I36 -> 11372.64 | J18: ='Cost Model'!J36 -> 14988.896
A19: Earnings After Tax (EAT) | C19: =C17-C18 -> 2338.8 | D19: =D17-D18 -> 6029.82 | E19: =E17-E18 -> 8329.45 | F19: =F17-F18 -> 9628.79 | G19: =G17-G18 -> 16063.232 | H19: =H17-H18 -> 20051.006 | I19: =I17-I18 -> 33132.394 | J19: =J17-J18 -> 43667.786
A20: Dividend Paid | C20: 0 | D20: 0 | E20: 0 | F20: 0 | G20: ='Cost Model'!G39 -> 0 | H20: ='Cost Model'!H39 -> 0 | I20: ='Cost Model'!I39 -> 0 | J20: ='Cost Model'!J39 -> 0
A21: Profit Transferred to Reserve | C21: =C19-C20 -> 2338.8 | D21: =D19-D20 -> 6029.82 | E21: =E19-E20 -> 8329.45 | F21: =F19-F20 -> 9628.79 | G21: =G19-G20 -> 16063.232 | H21: =H19-H20 -> 20051.006 | I21: =I19-I20 -> 33132.394 | J21: =J19-J20 -> 43667.786

Sheet CF
A1: Cash Flow Statement
A2: Figures in lakhs
A3: Particular/Years | B3: Comments | C3: 2021-22 A | D3: 2022-23 A | E3: 2023-24 A | F3: 2024-25 A | G3: 2025-26 E | H3: 2026-27 E | I3: 2027-28 E | J3: 2028-29 E
A4: A. OPERATING ACTIVITIES
A5: Profit before income tax | C5: 3152.59 | D5: 8067.65 | E5: 11131.21 | F5: 13006.86 | G5: =IS!G17 -> 21576.911 | H5: =IS!H17 -> 26933.481 | I5: =IS!I17 -> 44505.034 | J5: =IS!J17 -> 58656.682
A6: Adjustments to reconcile profit before tax to net cash flows :
A7: Depreciation and amortization expense | C7: 3150.86 | D7: 3463.09 | E7: 4867.46 | F7: 6300.31 | G7: =IS!G11 -> 8320.7453 | H7: =IS!H11 -> 8029.9153 | I7: =IS!I11 -> 7883.2206 | J7: =IS!J11 -> 7859.9866
A8: Write off / loss on sale of property, plant & equipment | C8: 23.72 | D8: 0 | E8: 8.87 | F8: 21.26 | G8: 0 | H8: 0 | I8: 0 | J8: 0
A9: Profit on Sale of property, plant & equipments | C9: 0 | D9: -12.81 | E9: -55.76 | F9: 54.18 | G9: 0 | H9: 0 | I9: 0 | J9: 0
A10: Interest expense | C10: 1611.28 | D10: 1404.56 | E10: 1599.14 | F10: 1926.88 | G10: =IS!G13 -> 2963.3104 | H10: =IS!H13 -> 2783.3025 | I10: =IS!I13 -> 2650.9586 | J10: =IS!J13 -> 2556.2267
A11: Effect of exchange rates on translation of operating cash flows | C11: 0 | D11: -0.16 | E11: 0.16 | F11: 0 | G11: 0 | H11: 0 | I11: 0 | J11: 0
A12: Interest income | C12: -203.43 | D12: -1193.99 | E12: -1828.7 | F12: -2184.7 | G12: =-IS!G14 -> -2429.98 | H12: =-IS!H14 -> -2429.98 | I12: =-IS!I14 -> -2429.98 | J12: =-IS!J14 -> -2429.98
A13: Provisions/liabilities no longer required written back | C13: -106.86 | D13: -147.42 | E13: -166.04 | F13: -75.82 | G13: 0 | H13: 0 | I13: 0 | J13: 0
A14: Share of profit of joint venture | C14: -2.4 | D14: -49.68 | E14: -67.31 | F14: 185.97 | G14: 0 | H14: 0 | I14: 0 | J14: 0
A15: Share options lapsed | C15: -9.41 | D15: 0 | E15: 0 | F15: 0 | G15: 0 | H15: 0 | I15: 0 | J15: 0
A16: Unrealized foreign exchange gain | C16: -9.35 | D16: -2.15 | E16: -46.36 | F16: -14.5 | G16: 0 | H16: 0 | I16: 0 | J16: 0
A17: Fair value gain on investments carried at fair value through profit or loss | C17: 0 | D17: 0 | E17: -22.16 | F17: -42.53 | G17: 0 | H17: 0 | I17: 0 | J17: 0
A18: Change in fair value of derivative contracts | C18: 0 | D18: 0 | E18: 0 | F18: 13.43 | G18: 0 | H18: 0 | I18: 0 | J18: 0
A19: Gain on deemed disposal of subsidiary | C19: 0 | D19: 0 | E19: -225.8 | F19: 0 | G19: 0 | H19: 0 | I19: 0 | J19: 0
A20: Rent waiver on lease liabilities | C20: -804.46 | D20: 0 | E20: 0 | F20: 0 | G20: 0 | H20: 0 | I20: 0 | J20: 0
A21: Gain on termination of lease contracts | C21: -34.42 | D21: -26.84 | E21: -9.18 | F21: -112.28 | G21: 0 | H21: 0 | I21: 0 | J21: 0
A22: Allowance for bad and doubtful debts/(written back) | C22: -86.7 | D22: -5.73 | E22: 1.26 | F22: 2.71 | G22: 0 | H22: 0 | I22: 0 | J22: 0
A23: Allowance for bad and doubtful advances/recoverable | C23: 15 | D23: 0 | E23: 0 | F23: 107.14 | G23: 0 | H23: 0 | I23: 0 | J23: 0
A24: Advances / deposits / Bad debts written off | C24: 269.19 | D24: 15.98 | E24: 39.4 | F24: 22.98 | G24: 0 | H24: 0 | I24: 0 | J24: 0
A25: Cash generated from operations before working capital changes | C25: =SUM(C5:C24) -> 6965.61 | D25: =SUM(D5:D24) -> 11512.5 | E25: =SUM(E5:E24) -> 15226.19 | F25: =SUM(F5:F24) -> 19211.89 | G25: =SUM(G5:G24) -> 30430.986 | H25: =SUM(H5:H24) -> 35316.719 | I25: =SUM(I5:I24) -> 52609.233 | J25: =SUM(J5:J24) -> 66642.915
A26: Movements in working capital:
A27: (Increase) in loans | C27: -2.69 | D27: -0.34 | E27: 5.52 | F27: 20.75 | G27: =BS!F24-BS!G24 -> 0 | H27: =BS!G24-BS!H24 -> 0 | I27: =BS!H24-BS!I24 -> 0 | J27: =BS!I24-BS!J24 -> 0
A28: (Increase)/ Decrease in other financial assets | C28: -4.06 | D28: -953.36 | E28: -511.77 | F28: -727.3 | G28: =BS!F25-BS!G25 -> 0 | H28: =BS!G25-BS!H25 -> 0 | I28: =BS!H25-BS!I25 -> 0 | J28: =BS!I25-BS!J25 -> 0
A29: (Increase)/ Decrease in other assets | C29: -1504.05 | D29: -1432.41 | E29: 762.89 | F29: -793.17 | G29: =BS!F26-BS!G26 -> 0 | H29: =BS!G26-BS!H26 -> 0 | I29: =BS!H26-BS!I26 -> 0 | J29: =BS!I26-BS!J26 -> 0
A30: (Increase)/ Decrease in inventories | C30: -5216.17 | D30: -8994 | E30: -9981.89 | F30: -15297.88 | G30: =BS!F20-BS!G20 -> -17880.516 | H30: =BS!G20-BS!H20 -> -17055.715 | I30: =BS!H20-BS!I20 -> -12503.828 | J30: =BS!I20-BS!J20 -> -19599.743
A31: (Increase)/ Decrease in trade receivables | C31: 693.82 | D31: -108.22 | E31: -959.21 | F31: -294.45 | G31: =BS!F21-BS!G21 -> 72.596008 | H31: =BS!G21-BS!H21 -> -601.72827 | I31: =BS!H21-BS!I21 -> -452.99981 | J31: =BS!I21-BS!J21 -> -700.44186
A32: Increase in employee benefit obligations | C32: 62.34 | D32: 92.21 | E32: 114.77 | F32: 37.73 | G32: =BS!G49-BS!F49 -> 0 | H32: =BS!H49-BS!G49 -> 0 | I32: =BS!I49-BS!H49 -> 0 | J32: =BS!J49-BS!I49 -> 0
A33: Increase in trade payables | C33: 1220.43 | D33: 1406.13 | E33: 92.52 | F33: -727.4 | G33: =BS!G46-BS!F46 -> 9108.8831 | H33: =BS!H46-BS!G46 -> 7902.5888 | I33: =BS!I46-BS!H46 -> 6885.8193 | J33: =BS!J46-BS!I46 -> 12551.121
A34: Increase/(Decrease) in other financial liabilities | C34: 39.62 | D34: 146.53 | E34: 1017.96 | F34: -573.17 | G34: =BS!G47-BS!F47 -> 0 | H34: =BS!H47-BS!G47 -> 0 | I34: =BS!I47-BS!H47 -> 0 | J34: =BS!J47-BS!I47 -> 0
A35: Increase/ (Decrease) in other current liabilities | C35: 387.06 | D35: 148.67 | E35: 101.49 | F35: 584.39 | G35: =BS!G48-BS!F48 -> 0 | H35: =BS!H48-BS!G48 -> 0 | I35: =BS!I48-BS!H48 -> 0 | J35: =BS!J48-BS!I48 -> 0
A36: Cash flow from operations | C36: =SUM(C25:C35) -> 2641.91 | D36: =SUM(D25:D35) -> 1817.71 | E36: =SUM(E25:E35) -> 5868.47 | F36: =SUM(F25:F35) -> 1441.39 | G36: =SUM(G25:G35) -> 21731.95 | H36: =SUM(H25:H35) -> 25561.865 | I36: =SUM(I25:I35) -> 46538.224 | J36: =SUM(J25:J35) -> 58893.852
A37: Income tax paid (net) | C37: -977.31 | D37: -2032.24 | E37: -2787.08 | F37: -3470.04 | G37: =-IS!G18 -> -5513.6782 | H37: =-IS!H18 -> -6882.4749 | I37: =-IS!I18 -> -11372.64 | J37: =-IS!J18 -> -14988.896
A38: Net cash flow from operating activities (A) | C38: =C36+C37 -> 1664.6 | D38: =D36+D37 -> -214.53 | E38: =E36+E37 -> 3081.39 | F38: =F36+F37 -> -2028.65 | G38: =G36+G37 -> 16218.272 | H38: =H36+H37 -> 18679.39 | I38: =I36+I37 -> 35165.584 | J38: =J36+J37 -> 43904.956
A39: B. INVESTING ACTIVITIES
A40: Acquisition of property, plant and equipment | B40: Including intangible assets,capital work in progress, intangible assets under development and capital advances | C40: -2373.36 | D40: -5663.64 | E40: -3944.76 | F40: -7933.01 | G40: =-'Capex Schedule'!G103 -> -1896.6287 | H40: =-'Capex Schedule'!H103 -> -1847.5359 | I40: =-'Capex Schedule'!I103 -> -1885.3135 | J40: =-'Capex Schedule'!J103 -> -4402.7954
A41: Proceeds from sale of property, plant and equipment | C41: 19.76 | D41: 108.95 | E41: 788.31 | F41: 595.04 | G41: =-'Capex Schedule'!G104 -> 0 | H41: =-'Capex Schedule'!H104 -> 0 | I41: =-'Capex Schedule'!I104 -> 0 | J41: =-'Capex Schedule'!J104 -> 0
A42: Payment towards purchase of investments | C42: -75 | D42: -112.76 | E42: -100 | F42: 0 | G42: 0 | H42: 0 | I42: 0 | J42: 0
A43: Payment towards acquistion of associate | C43: 0 | D43: 0 | E43: -1842.93 | F43: -472.54 | G43: 0 | H43: 0 | I43: 0 | J43: 0
A44: Investment in bank deposits | B44: Having original maturity of more than three months | C44: -10.93 | D44: -20708.48 | E44: -8370.47 | F44: 10155.7 | G44: 0 | H44: 0 | I44: 0 | J44: 0
A45: Interest received | C45: 62.03 | D45: 754.56 | E45: 1189.75 | F45: 2313.41 | G45: =IS!G14 -> 2429.98 | H45: =IS!H14 -> 2429.98 | I45: =IS!I14 -> 2429.98 | J45: =IS!J14 -> 2429.98
A46: Net cash (used in) investing activities (B) | C46: =SUM(C40:C45) -> -2377.5 | D46: =SUM(D40:D45) -> -25621.37 | E46: =SUM(E40:E45) -> -12280.1 | F46: =SUM(F40:F45) -> 4658.6 | G46: =SUM(G40:G45) -> 533.35129 | H46: =SUM(H40:H45) -> 582.44409 | I46: =SUM(I40:I45) -> 544.66652 | J46: =SUM(J40:J45) -> -1972.8154
A47: C. FINANCING ACTIVITIES
A48: Proceeds from issue of equity share capital (including premium) | C48: 5144.36 | D48: 37500 | E48: 17499.82 | F48: 0 | G48: 0 | H48: 0 | I48: 0 | J48: 0
A49: Share issue expenses | C49: -384.58 | D49: -3531.05 | E49: -540.18 | F49: 0 | G49: 0 | H49: 0 | I49: 0 | J49: 0
A50: Proceeds from non-current borrowings | C50: 2225.63 | D50: 178.6 | E50: 26.75 | F50: 0 | G50: 0 | H50: 0 | I50: 0 | J50: 0
A51: Repayment of non-current borrowings | C51: -1084.32 | D51: -3081.45 | E51: -112.05 | F51: -4.83 | G51: 0 | H51: 0 | I51: 0 | J51: 0
A52: Proceeds from current borrowings having maturity period more than 3 months | C52: 739.78 | D52: 0 | E52: 0 | F52: 0 | G52: 0 | H52: 0 | I52: 0 | J52: 0
A53: Repayment of current borrowing having maturity period more than 3 months | C53: -351.24 | D53: 0 | E53: 0 | F53: 0 | G53: 0 | H53: 0 | I53: 0 | J53: 0
A54: Proceeds from/repayments of other current borrowings (net) | C54: -786.45 | D54: -2240.36 | E54: -43.87 | F54: -469.01 | G54: 0 | H54: 0 | I54: 0 | J54: 0
A55: Payment of principal portion of lease liabilities | C55: -1204.74 | D55: -2402.73 | E55: -2814.86 | F55: -3389.55 | G55: =-'Lease Schedule '!G27 -> -6156.1749 | H55: =-'Lease Schedule '!H27 -> -5779.1598 | I55: =-'Lease Schedule '!I27 -> -5501.974 | J55: =-'Lease Schedule '!J27 -> -5303.564
A56: Interest paid on lease liabilities | C56: -1020.83 | D56: -1152.91 | E56: -1511.36 | F56: -1824.71 | G56: 0 | H56: 0 | I56: 0 | J56: 0
A57: Interest expense paid | C57: -627.22 | D57: -413.65 | E57: -36.49 | F57: -151.75 | G57: =-IS!G13 -> -2963.3104 | H57: =-IS!H13 -> -2783.3025 | I57: =-IS!I13 -> -2650.9586 | J57: =-IS!J13 -> -2556.2267
A58: Net cash flow from/(used in) financing activities (C) | C58: =SUM(C48:C57) -> 2650.39 | D58: =SUM(D48:D57) -> 24856.45 | E58: =SUM(E48:E57) -> 12467.76 | F58: =SUM(F48:F57) -> -5839.85 | G58: =SUM(G48:G57) -> -9119.4854 | H58: =SUM(H48:H57) -> -8562.4623 | I58: =SUM(I48:I57) -> -8152.9326 | J58: =SUM(J48:J57) -> -7859.7907
A60: NET INCREASE IN CASH AND CASH EQUIVALENTS (A+B+C) | C60: =C38+C46+C58 -> 1937.49 | D60: =D38+D46+D58 -> -979.45 | E60: =E38+E46+E58 -> 3269.05 | F60: =F38+F46+F58 -> -3209.9 | G60: =G38+G46+G58 -> 7632.1376 | H60: =H38+H46+H58 -> 10699.372 | I60: =I38+I46+I58 -> 27557.318 | J60: =J38+J46+J58 -> 34072.35
A61: Cash and cash equivalents at the beginning of the year | C61: 1830.83 | D61: 3768.32 | E61: 2788.87 | F61: 6057.91 | G61: =F62 -> 2848.01 | H61: =G62 -> 10480.148 | I61: =H62 -> 21179.519 | J61: =I62 -> 48736.838
A62: Cash and cash equivalents at the end of the year | C62: =C60+C61 -> 3768.32 | D62: =D60+D61 -> 2788.87 | E62: =E60+E61 -> 6057.92 | F62: =F60+F61 -> 2848.01 | G62: =G60+G61 -> 10480.148 | H62: =H60+H61 -> 21179.519 | I62: =I60+I61 -> 48736.838 | J62: =J60+J61 -> 82809.188

Sheet Revenue Model
A1: Revenue Model
A2: Figures in lakhs
A3: Particular/Years | B3: Comments | C3: 2021-22 A | D3: 2022-23 A | E3: 2023-24 A | F3: 2024-25 A | G3: 2025-26 E | H3: 2026-27 E | I3: 2027-28 E | J3: 2028-29 E
A4: =IS!A4 -> Revenue from operations | C4: =IS!C4 -> 57728.37 | D4: =IS!D4 -> 78853.37 | E4: =IS!E4 -> 99899.21 | F4: =IS!F4 -> 125162.71 | G4: =G9+G26 -> 185499.77 | H4: =H9+H26 -> 238779.17 | I4: =I9+I26 -> 292842.84 | J4: =J9+J26 -> 365888.92
A5: YoY % Growth in Revneue from operations | C5: - | D5: =D4/C4-1 -> 0.36593793 | E5: =E4/D4-1 -> 0.26689842 | F5: =F4/E4-1 -> 0.25288989 | G5: =G4/F4-1 -> 0.48206898 | H5: =H4/G4-1 -> 0.28722086 | I5: =I4/H4-1 -> 0.22641703 | J5: =J4/I4-1 -> 0.24943782
A7: ONLINE SALES
A8: Online sales % of total Revnue | B8: From Equentis for 2024 &Tijori Finance for 2025 | C8: 0.2 | D8: 0.31 | E8: 0.3 | F8: 0.427 | G8: =G9/G4 -> 0.37454397 | H8: =H9/H4 -> 0.37826233 | I8: =I9/I4 -> 0.40095744 | J8: =J9/J4 -> 0.41718336
A9: Online Sales | C9: =C4*C8 -> 11545.674 | D9: =D4*D8 -> 24444.545 | E9: =E4*E8 -> 29969.763 | F9: =F4*F8 -> 53444.477 | G9: =F9*(1+Assumption!G7) -> 69477.82 | H9: =G9*(1+Assumption!H7) -> 90321.166 | I9: =H9*(1+Assumption!I7) -> 117417.52 | J9: =I9*(1+Assumption!J7) -> 152642.77
A11: STORE SALES
A12: Number of Stores | C12: 50 | D12: 56 | E12: 63 | F12: 73 | G12: =Assumption!G9 -> 100 | H12: =Assumption!H9 -> 108 | I12: =Assumption!I9 -> 116 | J12: =Assumption!J9 -> 124
A13: Number of Stores Newly opened during the year | C13: =D12-C12 -> 6 | D13: =E12-D12 -> 7 | E13: =F12-E12 -> 10 | F13: =G12-F12 -> 27 | G13: =H12-G12 -> 8 | H13: =I12-H12 -> 8 | I13: =J12-I12 -> 8 | J13: 20
A15: Existing Store (Age>2 years) | C15: =C12 -> 50 | D15: =C15+C16 -> 50 | E15: =D15+D16 -> 56 | F15: =E15+E16 -> 63 | G15: =F15+F16 -> 73 | H15: =G15+G16 -> 100 | I15: =H15+H16 -> 108 | J15: =I15+I16 -> 116
A16: New Store (Age between 1 and 2 years) | D16: =C17 -> 6 | E16: =D17 -> 7 | F16: =E17 -> 10 | G16: =F17 -> 27 | H16: =G17 -> 8 | I16: =H17 -> 8 | J16: =I17 -> 8
A17: New Store (Age < 1 year) | C17: =C13 -> 6 | D17: =D13 -> 7 | E17: =E13 -> 10 | F17: =F13 -> 27 | G17: =G13 -> 8 | H17: =H13 -> 8 | I17: =I13 -> 8 | J17: =J13 -> 20
A19: Revenue Per Existing Store | C19: =C26/C15 -> 923.65392 | D19: =D26/D15 -> 1088.1765 | E19: =E26/E15 -> 1248.7401 | F19: =F26/F15 -> 1138.3846 | G19: =F19*(1+Assumption!G10) -> 1252.2231 | H19: =G19*(1+Assumption!H10) -> 1377.4454 | I19: =H19*(1+Assumption!I10) -> 1515.19 | J19: =I19*(1+Assumption!J10) -> 1666.709
A20: Revenue Per New Store(Age between 1 and 2 years) | G20: =G19/(1+Assumption!G11) -> 782.63945 | H20: =H19/(1+Assumption!H11) -> 860.90339 | I20: =I19/(1+Assumption!I11) -> 946.99373 | J20: =J19/(1+Assumption!J11) -> 1041.6931
A21: Revenue Per New Store(Age < 1 years) | G21: =G20/(1+Assumption!G12) -> 434.79969 | H21: =H20/(1+Assumption!H12) -> 478.27966 | I21: =I20/(1+Assumption!I12) -> 526.10763 | J21: =J20/(1+Assumption!J12) -> 578.71839
A23: Revenue from Existing Store | G23: =G19*G15 -> 91412.287 | H23: =H19*H15 -> 137744.54 | I23: =I19*I15 -> 163640.52 | J23: =J19*J15 -> 193338.24
A24: Revenue from New Store(Age between 1 and 2 years) | G24: =G20*G16 -> 21131.265 | H24: =H20*H16 -> 6887.2271 | I24: =I20*I16 -> 7575.9498 | J24: =J20*J16 -> 8333.5448
A25: Revenue from New Store(Age < 1 years) | G25: =G21*G17 -> 3478.3975 | H25: =H21*H17 -> 3826.2373 | I25: =I21*I17 -> 4208.861 | J25: =J21*J17 -> 11574.368
A26: TOTAL STORE SALES | C26: =C4-C9 -> 46182.696 | D26: =D4-D9 -> 54408.825 | E26: =E4-E9 -> 69929.447 | F26: =F4-F9 -> 71718.233 | G26: =SUM(G23:G25) -> 116021.95 | H26: =SUM(H23:H25) -> 148458.01 | I26: =SUM(I23:I25) -> 175425.33 | J26: =SUM(J23:J25) -> 213246.15

Sheet Cost Model
A1: Cost Model
A2: Figures in lakhs
A3: Particular/Years | B3: Comments | C3: 2021-22 A | D3: 2022-23 A | E3: 2023-24 A | F3: 2024-25 A | G3: 2025-26 E | H3: 2026-27 E | I3: 2027-28 E | J3: 2028-29 E
A5: =IS!A4 -> Revenue from operations | C5: =IS!C4 -> 57728.37 | D5: =IS!D4 -> 78853.37 | E5: =IS!E4 -> 99899.21 | F5: =IS!F4 -> 125162.71 | G5: =IS!G4 -> 185499.77 | H5: =IS!H4 -> 238779.17 | I5: =IS!I4 -> 292842.84 | J5: =IS!J4 -> 365888.92
A6: COGS
A7: COGS/Revenue from operations | C7: =C8/C5 -> 0.71217046 | D7: =D8/D5 -> 0.6903762 | E7: =E8/E5 -> 0.69906509 | F7: =F8/F5 -> 0.7004301 | G7: =Assumption!G16 -> 0.69 | H7: =Assumption!H16 -> 0.72 | I7: =Assumption!I16 -> 0.7 | J7: =Assumption!J16 -> 0.7
A8: =IS!A5 -> Cost of Goods Sold | C8: =IS!C5 -> 41112.44 | D8: =IS!D5 -> 54438.49 | E8: =IS!E5 -> 69836.05 | F8: =IS!F5 -> 87667.73 | G8: =G5*'Cost Model'!G7 -> 127994.84 | H8: =H5*'Cost Model'!H7 -> 171921 | I8: =I5*'Cost Model'!I7 -> 204989.99 | J8: =J5*'Cost Model'!J7 -> 256122.25
A10: Employee benefits expense
A11: Total Employees | D11: =SUM(D13:D15) -> 542 | E11: =SUM(E13:E15) -> 632 | F11: =SUM(F13:F15) -> 780 | G11: =SUM(G13:G15) -> 1105 | H11: =SUM(H13:H15) -> 1193 | I11: =SUM(I13:I15) -> 1281 | J11: =SUM(J13:J15) -> 1369
A13: Number of Board of Director | D13: 12 | E13: 10 | F13: 3 | G13: =Assumption!G18 -> 3 | H13: =Assumption!H18 -> 3 | I13: =Assumption!I18 -> 3 | J13: =Assumption!J18 -> 3
A14: Number of Key Managerial Personnel | D14: 3 | E14: 5 | F14: 2 | G14: =Assumption!G19 -> 2 | H14: =Assumption!H19 -> 2 | I14: =Assumption!I19 -> 2 | J14: =Assumption!J19 -> 2
A15: Number of Employee other than BOD and KMP | D15: 527 | E15: 617 | F15: 775 | G15: =G21*G22 -> 1100 | H15: =H21*H22 -> 1188 | I15: =I21*I22 -> 1276 | J15: =J21*J22 -> 1364
A17: Median Remuneration of BOD | D17: 11.15 | E17: 39.25 | F17: 262.383 | G17: =F17*(1+Assumption!G21) -> 267.63066 | H17: =G17*(1+Assumption!H21) -> 272.98327 | I17: =H17*(1+Assumption!I21) -> 278.44294 | J17: =I17*(1+Assumption!J21) -> 284.0118
A18: Median Remuneration of KMP | D18: 109.09816 | E18: 147.89 | F18: 83.2135 | G18: =F18*(1+Assumption!G22) -> 102.3526 | H18: =G18*(1+Assumption!H22) -> 125.8937 | I18: =H18*(1+Assumption!I22) -> 154.84926 | J18: =I18*(1+Assumption!J22) -> 190.46459
A19: Median Remuneration of Employee othet than BOD and KMP | D19: 5.65353 | E19: 5.86728 | F19: 6.1765 | G19: =F19*(1+Assumption!G23) -> 6.833062 | H19: =G19*(1+Assumption!H23) -> 7.5594164 | I19: =H19*(1+Assumption!I23) -> 8.3629824 | J19: =I19*(1+Assumption!J23) -> 9.2519674
A21: =Assumption!A9 -> Number of Stores | D21: =Assumption!D9 -> 56 | E21: =Assumption!E9 -> 63 | F21: =Assumption!F9 -> 73 | G21: =Assumption!G9 -> 100 | H21: =Assumption!H9 -> 108 | I21: =Assumption!I9 -> 116 | J21: =Assumption!J9 -> 124
A22: Employee per store | D22: =D15/D21 -> 9.4107143 | E22: =E15/E21 -> 9.7936508 | F22: =F15/F21 -> 10.616438 | G22: =Assumption!G20 -> 11 | H22: =Assumption!H20 -> 11 | I22: =Assumption!I20 -> 11 | J22: =Assumption!J20 -> 11
A24: =IS!A7 -> Employee benefits expense | C24: =IS!C7 -> 4238.15 | D24: =IS!D7 -> 5268.17 | E24: =IS!E7 -> 7036.38 | F24: =IS!F7 -> 8533.57 | G24: =(G13*G17)+(G14*G18)+(G15*G19) -> 8523.9653 | H24: =(H13*H17)+(H14*H18)+(H15*H19) -> 10051.324 | I24: =(I13*I17)+(I14*I18)+(I15*I19) -> 11816.193 | J24: =(J13*J17)+(J14*J18)+(J15*J19) -> 13852.648
A26: Advertisement and sales promotion expense
A27: Advertisement and sales promotion expense/Revenue from operations | C27: =C28/C5 -> 0.038547771 | D27: =D28/D5 -> 0.034030125 | E27: =E28/E5 -> 0.021022889 | F27: =F28/F5 -> 0.019442612 | G27: =Assumption!G25 -> 0.04 | H27: =Assumption!H25 -> 0.03 | I27: =Assumption!I25 -> 0.02 | J27: =Assumption!J25 -> 0.02
A28: =IS!A8 -> Advertisement and sales promotion expense | C28: =IS!C8 -> 2225.3 | D28: =IS!D8 -> 2683.39 | E28: =IS!E8 -> 2100.17 | F28: =IS!F8 -> 2433.49 | G28: =G5*G27 -> 7419.9908 | H28: =H5*H27 -> 7163.3752 | I28: =I5*I27 -> 5856.8569 | J28: =J5*J27 -> 7317.7785
A30: Other Expenses
A31: Other Expenses/Revenue | C31: =C32/C5 -> 0.059970167 | D31: =D32/D5 -> 0.063690873 | E31: =E32/E5 -> 0.057609364 | F31: =F32/F5 -> 0.060089143 | G31: =Assumption!G27 -> 0.06 | H31: =Assumption!H27 -> 0.06 | I31: =Assumption!I27 -> 0.06 | J31: =Assumption!J27 -> 0.06
A32: =IS!A9 -> Other Expense | C32: =IS!C9 -> 3461.98 | D32: =IS!D9 -> 5022.24 | E32: =IS!E9 -> 5755.13 | F32: =IS!F9 -> 7520.92 | G32: =G5*G31 -> 11129.986 | H32: =H5*H31 -> 14326.75 | I32: =I5*I31 -> 17570.571 | J32: =J5*J31 -> 21953.335
A34: Tax Expense
A35: Effective Tax Rate | C35: =IS!C18/IS!C17 -> 0.25813379 | D35: =IS!D18/IS!D17 -> 0.25259276 | E35: =IS!E18/IS!E17 -> 0.25170309 | F35: =IS!F18/IS!F17 -> 0.25971449 | G35: =Assumption!G29 -> 0.25553603 | H35: =Assumption!H29 -> 0.25553603 | I35: =Assumption!I29 -> 0.25553603 | J35: =Assumption!J29 -> 0.25553603
A36: =IS!A18 -> Tax Expense | C36: =IS!C18 -> 813.79 | D36: =IS!D18 -> 2037.83 | E36: =IS!E18 -> 2801.76 | F36: =IS!F18 -> 3378.07 | G36: =IS!G17*'Cost Model'!G35 -> 5513.6782 | H36: =IS!H17*'Cost Model'!H35 -> 6882.4749 | I36: =IS!I17*'Cost Model'!I35 -> 11372.64 | J36: =IS!J17*'Cost Model'!J35 -> 14988.896
A38: Dividend
A39: =IS!A20 -> Dividend Paid | C39: =IS!C20 -> 0 | D39: =IS!D20 -> 0 | E39: =IS!E20 -> 0 | F39: =IS!F20 -> 0 | G39: =Assumption!G31 -> 0 | H39: =Assumption!H31 -> 0 | I39: =Assumption!I31 -> 0 | J39: =Assumption!J31 -> 0

Sheet Capex Schedule
A1: Capex Schedule
A2: Figures in lakhs
A3: Particular/Years | B3: Comments | C3: 2021-22 A | D3: 2022-23 A | E3: 2023-24 A | F3: 2024-25 A | G3: 2025-26 E | H3: 2026-27 E | I3: 2027-28 E | J3: 2028-29 E
A5: Leasehold Improvements
A6: Opening Gross Block | C6: 2360.53 | D6: 2723.07 | E6: 3422.09 | F6: 4335.95 | G6: 5858.75 | H6: =G9 -> 6453.55 | I6: =H9 -> 7048.35 | J6: =I9 -> 7643.15
A7: Add:Capex | C7: 485.3 | D7: 933.43 | E7: 1021.76 | F7: 2007.47 | G7: =G22*'Revenue Model'!G13 -> 594.8 | H7: =H22*'Revenue Model'!H13 -> 594.8 | I7: =I22*'Revenue Model'!I13 -> 594.8 | J7: =J22*'Revenue Model'!J13 -> 1487
A8: Less:Disposal/Sale | C8: -122.77 | D8: -234.41 | E8: -107.9 | F8: -484.67 | G8: 0 | H8: 0 | I8: 0 | J8: 0
A9: Closing Gross Block | C9: 2723.06 | D9: 3422.09 | E9: 4335.95 | F9: 5858.75 | G9: =G6+G7-G8 -> 6453.55 | H9: =H6+H7+H8 -> 7048.35 | I9: =I6+I7+I8 -> 7643.15 | J9: =J6+J7+J8 -> 9130.15
A11: Opening Accumulated Depreciation | C11: 1084.29 | D11: 1315.21 | E11: 1498.96 | F11: 2041.87 | G11: 2343.86 | H11: =G14 -> 3180.8243 | I11: =H14 -> 4102.76 | J11: =I14 -> 5109.6671
A12: Depreciation for the year | C12: 353.69 | D12: 418.16 | E12: 650.81 | F12: 786.66 | G12: =G6/G18 -> 836.96429 | H12: =H6/H18 -> 921.93571 | I12: =I6/I18 -> 1006.9071 | J12: =J6/J18 -> 1091.8786
A13: Accumulated depreciation on disposals | C13: -122.77 | D13: -234.41 | E13: -107.9 | F13: -484.67 | G13: 0 | H13: 0 | I13: 0 | J13: 0
A14: Ending Accumulated Depreciation | C14: 1315.21 | D14: 1498.96 | E14: 2041.87 | F14: 2343.86 | G14: =G11+G12+G13 -> 3180.8243 | H14: =H11+H12+H13 -> 4102.76 | I14: =I11+I12+I13 -> 5109.6671 | J14: =J11+J12+J13 -> 6201.5457
A16: Closing Net Block | C16: 1407.85 | D16: 1923.13 | E16: 2294.08 | F16: 3514.89 | G16: =G9-G14 -> 3272.7257 | H16: =H9-H14 -> 2945.59 | I16: =I9-I14 -> 2533.4829 | J16: =J9-J14 -> 2928.6043
A18: Total Useful Life | B18: Cl.Gross Block/Depri for the year | C18: =C9/C12 -> 7.699002 | D18: =D9/D12 -> 8.1836857 | E18: =E9/E12 -> 6.6623899 | F18: =F9/F12 -> 7.4476267 | G18: =Assumption!G36 -> 7 | H18: =Assumption!H36 -> 7 | I18: =Assumption!I36 -> 7 | J18: =Assumption!J36 -> 7
A19: Age | B19: Cl.Acc Depri/Depri for the year | C19: =C14/C12 -> 3.7185388 | D19: =D14/D12 -> 3.5846566 | E19: =E14/E12 -> 3.1374287 | F19: =F14/F12 -> 2.9795083 | G19: =G14/G12 -> 3.8004301 | H19: =H14/H12 -> 4.4501584 | I19: =I14/I12 -> 5.074616 | J19: =J14/J12 -> 5.6797027
A20: Remaining Useful Life | B20: Cl.Net Bloc/Depri for the year | C20: =C16/C12 -> 3.9804631 | D20: =D16/D12 -> 4.5990291 | E20: =E16/E12 -> 3.5249612 | F20: =F16/F12 -> 4.4681184 | G20: =G16/G12 -> 3.9102334 | H20: =H16/H12 -> 3.1950058 | I20: =I16/I12 -> 2.5161038 | J20: =J16/J12 -> 2.6821703
A22: Capex/Number of new Store Opened | C22: =C7/'Revenue Model'!C13 -> 80.883333 | D22: =D7/'Revenue Model'!D13 -> 133.34714 | E22: =E7/'Revenue Model'!E13 -> 102.176 | F22: =F7/'Revenue Model'!F13 -> 74.350741 | G22: =Assumption!G37 -> 74.35 | H22: =Assumption!H37 -> 74.35 | I22: =Assumption!I37 -> 74.35 | J22: =Assumption!J37 -> 74.35
A24: Plant and Equiment
A25: Opening Gross Block | C25: 349.39 | D25: 353.35 | E25: 376.12 | F25: 401.58 | G25: 667.91 | H25: =G28 -> 667.91 | I25: =H28 -> 667.91 | J25: =I28 -> 667.91
A26: Add:Capex | C26: 3.96 | D26: 53.6 | E26: 25.53 | F26: 266.33 | G26: =Assumption!G40 -> 0 | H26: =Assumption!H40 -> 0 | I26: =Assumption!I40 -> 0 | J26: =Assumption!J40 -> 0
A27: Less:Disposal/Sale | C27: 0 | D27: -30.83 | E27: -0.07 | F27: 0 | G27: 0 | H27: 0 | I27: 0 | J27: 0
A28: Closing Gross Block | C28: 353.35 | D28: 376.12 | E28: 401.58 | F28: 667.91 | G28: =G25+G26-G27 -> 667.91 | H28: =H25+H26+H27 -> 667.91 | I28: =I25+I26+I27 -> 667.91 | J28: =J25+J26+J27 -> 667.91
A30: Opening Accumulated Depreciation | C30: 25.43 | D30: 45.2 | E30: 35.83 | F30: 63.35 | G30: 111.74 | H30: =G33 -> 160.13 | I30: =H33 -> 208.52 | J30: =I33 -> 256.91
A31: Depreciation for the year | C31: 19.77 | D31: 21.46 | E31: 27.59 | F31: 48.39 | G31: =G25/G37 -> 48.39 | H31: =H25/H37 -> 48.39 | I31: =I25/I37 -> 48.39 | J31: =J25/J37 -> 48.39
A32: Accumulated depreciation on disposals | C32: 0 | D32: -30.83 | E32: -0.07 | F32: 0 | G32: 0 | H32: 0 | I32: 0 | J32: 0
A33: Ending Accumulated Depreciation | C33: 45.2 | D33: 35.83 | E33: 63.35 | F33: 111.74 | G33: =G30+G31+G32 -> 160.13 | H33: =H30+H31+H32 -> 208.52 | I33: =I30+I31+I32 -> 256.91 | J33: =J30+J31+J32 -> 305.3
A35: Closing Net Block | C35: 308.15 | D35: 340.29 | E35: 338.23 | F35: 556.17 | G35: =G28-G33 -> 507.78 | H35: =H28-H33 -> 459.39 | I35: =I28-I33 -> 411 | J35: =J28-J33 -> 362.61
A37: Total Useful Life | B37: Cl.Gross Block/Depri for the year | C37: =C28/C31 -> 17.87304 | D37: =D28/D31 -> 17.526561 | E37: =E28/E31 -> 14.555274 | F37: =F28/F31 -> 13.802645 | G37: =Assumption!G41 -> 13.802645 | H37: =Assumption!H41 -> 13.802645 | I37: =Assumption!I41 -> 13.802645 | J37: =Assumption!J41 -> 13.802645
A38: Age | B38: Cl.Acc Depri/Depri for the year | C38: =C33/C31 -> 2.2862924 | D38: =D33/D31 -> 1.6696179 | E38: =E33/E31 -> 2.2961218 | F38: =F33/F31 -> 2.3091548 | G38: =G33/G31 -> 3.3091548 | H38: =H33/H31 -> 4.3091548 | I38: =I33/I31 -> 5.3091548 | J38: =J33/J31 -> 6.3091548
A39: Remaining Useful Life | B39: Cl.Net Bloc/Depri for the year | C39: =C35/C31 -> 15.586748 | D39: =D35/D31 -> 15.856943 | E39: =E35/E31 -> 12.259152 | F39: =F35/F31 -> 11.49349 | G39: =G35/G31 -> 10.49349 | H39: =H35/H31 -> 9.4934904 | I39: =I35/I31 -> 8.4934904 | J39: =J35/J31 -> 7.4934904
A41: Furniture and fittings
A42: Opening Gross Block | C42: 1774.05 | D42: 2205.14 | E42: 2807.13 | F42: 3777.7 | G42: 5649.73 | H42: =G46 -> 6209.73 | I42: =H46 -> 6769.73 | J42: =I46 -> 7329.73
A43: Add:Capex | C43: 463.73 | D43: 730.83 | E43: 1011.54 | F43: 2068.56 | G43: =G60*'Revenue Model'!G13 -> 560 | H43: =H60*'Revenue Model'!H13 -> 560 | I43: =I60*'Revenue Model'!I13 -> 560 | J43: =J60*'Revenue Model'!J13 -> 1400
A44: Less:Disposal/Sale | C44: -32.64 | D44: -128.84 | E44: -21.78 | F44: -196.53 | G44: 0 | H44: 0 | I44: 0 | J44: 0
A45: Deletion on account of deemed disposal of Subsidiary | C45: - | D45: - | E45: -19.19 | F45: -
A46: Closing Gross Block | C46: 2205.14 | D46: 2807.13 | E46: 3777.7 | F46: 5649.73 | G46: =G42+G43+G44+G45 -> 6209.73 | H46: =H42+H43+H44+H45 -> 6769.73 | I46: =I42+I43+I44+I45 -> 7329.73 | J46: =J42+J43+J44+J45 -> 8729.73
A48: Opening Accumulated Depreciation | C48: 576.92 | D48: 733.03 | E48: 870.47 | F48: 1246.17 | G48: 1645.45 | H48: =G52 -> 2210.423 | I48: =H52 -> 2831.396 | J48: =I52 -> 3508.369
A49: Depreciation for the year | C49: 182.18 | D49: 263.89 | E49: 395.88 | F49: 582.83 | G49: =G42/G56 -> 564.973 | H49: =H42/H56 -> 620.973 | I49: =I42/I56 -> 676.973 | J49: =J42/J56 -> 732.973
A50: Accumulated depreciation on disposals | C50: -26.07 | D50: -126.45 | E50: -18.91 | F50: -183.55 | G50: 0 | H50: 0 | I50: 0 | J50: 0
A51: Deletion on account of deemed disposal of Subsidiary | C51: - | D51: - | E51: -1.27 | F51: -
A52: Ending Accumulated Depreciation | C52: 733.03 | D52: 870.47 | E52: 1246.17 | F52: 1645.45 | G52: =G48+G49+G50 -> 2210.423 | H52: =H48+H49+H50 -> 2831.396 | I52: =I48+I49+I50 -> 3508.369 | J52: =J48+J49+J50 -> 4241.342
A54: Closing Net Block | C54: 1472.11 | D54: 1936.66 | E54: 2531.53 | F54: 4004.28 | G54: =G46-G52 -> 3999.307 | H54: =H46-H52 -> 3938.334 | I54: =I46-I52 -> 3821.361 | J54: =J46-J52 -> 4488.388
A56: Total Useful Life | B56: Cl.Gross Block/Depri for the year | C56: =C46/C49 -> 12.104183 | D56: =D46/D49 -> 10.6375 | E56: =E46/E49 -> 9.5425381 | F56: =F46/F49 -> 9.6936156 | G56: =Assumption!G44 -> 10 | H56: =Assumption!H44 -> 10 | I56: =Assumption!I44 -> 10 | J56: =Assumption!J44 -> 10
A57: Age | B57: Cl.Acc Depri/Depri for the year | C57: =C52/C49 -> 4.0236579 | D57: =D52/D49 -> 3.2986093 | E57: =E52/E49 -> 3.1478478 | F57: =F52/F49 -> 2.8232075 | G57: =G52/G49 -> 3.9124401 | H57: =H52/H49 -> 4.5596121 | I57: =I52/I49 -> 5.1824356 | J57: =J52/J49 -> 5.7864915
A58: Remaining Useful Life | B58: Cl.Net Bloc/Depri for the year | C58: =C54/C49 -> 8.0805248 | D58: =D54/D49 -> 7.3388912 | E58: =E54/E49 -> 6.3946903 | F58: =F54/F49 -> 6.8704082 | G58: =G54/G49 -> 7.0787577 | H58: =H54/H49 -> 6.3421985 | I58: =I54/I49 -> 5.6447761 | J58: =J54/J49 -> 6.123538
A60: Capex/Number of new store | C60: =C43/'Revenue Model'!C13 -> 77.288333 | D60: =D43/'Revenue Model'!D13 -> 104.40429 | E60: =E43/'Revenue Model'!E13 -> 101.154 | F60: =F43/'Revenue Model'!F13 -> 76.613333 | G60: =Assumption!G45 -> 70 | H60: =Assumption!H45 -> 70 | I60: =Assumption!I45 -> 70 | J60: =Assumption!J45 -> 70
A62: Office Equiments
A63: Opening Gross Block | C63: 240.76 | D63: 451.85 | E63: 555.06 | F63: 776.72 | G63: 1175.74 | H63: =IS!H4*'Capex Schedule'!H79 -> 1394.0475 | I63: =IS!I4*'Capex Schedule'!I79 -> 1563.2621 | J63: =IS!J4*'Capex Schedule'!J79 -> 1770.2544
A64: Add:Capex | C64: 214.13 | D64: 223.4 | E64: 264.38 | F64: 494.01 | G64: =H63-G63 -> 218.30746 | H64: =I63-H63 -> 169.21466 | I64: =J63-I63 -> 206.99223 | J64: =I64 -> 206.99223
A65: Less:Disposal/Sale | C65: -3.04 | D65: -120.19 | E65: -42.72 | F65: -94.99 | G65: 0 | H65: 0 | I65: 0 | J65: 0
A66: Closing Gross Block | C66: 451.85 | D66: 555.06 | E66: 776.72 | F66: 1175.74 | G66: =G63+G64-G65 -> 1394.0475 | H66: =H63+H64-H65 -> 1563.2621 | I66: =I63+I64-I65 -> 1770.2544 | J66: =J63+J64-J65 -> 1977.2466
A68: Opening Accumulated Depreciation | C68: 168.57 | D68: 240.37 | E68: 244.43 | F68: 390.64 | G68: 551.25 | H68: =G71 -> 786.398 | I68: =H71 -> 1065.2075 | J68: =I71 -> 1377.8599
A69: Depreciation for the year | C69: 74.3 | D69: 111.17 | E69: 163.25 | F69: 216.93 | G69: =G63/G75 -> 235.148 | H69: =H63/H75 -> 278.80949 | I69: =I63/I75 -> 312.65242 | J69: =J63/J75 -> 354.05087
A70: Accumulated depreciation on disposals | C70: -2.5 | D70: -107.11 | E70: -17.04 | F70: -56.32 | G70: 0 | H70: 0 | I70: 0 | J70: 0
A71: Ending Accumulated Depreciation | C71: 240.37 | D71: 244.43 | E71: 390.64 | F71: 551.25 | G71: =G68+G69-G70 -> 786.398 | H71: =H68+H69-H70 -> 1065.2075 | I71: =I68+I69-I70 -> 1377.8599 | J71: =J68+J69-J70 -> 1731.9108
A73: Closing Net Block | C73: 211.48 | D73: 310.63 | E73: 386.08 | F73: 624.49 | G73: =G66-G71 -> 607.64946 | H73: =H66-H71 -> 498.05463 | I73: =I66-I71 -> 392.39444 | J73: =J66-J71 -> 245.3358
A75: Total Useful Life | B75: Cl.Gross Block/Depri for the year | C75: =C66/C69 -> 6.0814266 | D75: =D66/D69 -> 4.9928938 | E75: =E66/E69 -> 4.757856 | F75: =F66/F69 -> 5.419905 | G75: =Assumption!G48 -> 5 | H75: =Assumption!H48 -> 5 | I75: =Assumption!I48 -> 5 | J75: =Assumption!J48 -> 5
A76: Age | B76: Cl.Acc Depri/Depri for the year | C76: =C71/C69 -> 3.2351279 | D76: =D71/D69 -> 2.1987047 | E76: =E71/E69 -> 2.3928943 | F76: =F71/F69 -> 2.5411423 | G76: =G71/G69 -> 3.3442683 | H76: =H71/H69 -> 3.8205568 | I76: =I71/I69 -> 4.4070022 | J76: =J71/J69 -> 4.8917004
A77: Remaining Useful Life | B77: Cl.Net Bloc/Depri for the year | C77: =C73/C69 -> 2.8462988 | D77: =D73/D69 -> 2.7941891 | E77: =E73/E69 -> 2.3649617 | F77: =F73/F69 -> 2.8787627 | G77: =G73/G69 -> 2.584115 | H77: =H73/H69 -> 1.7863618 | I77: =I73/I69 -> 1.25505 | J77: =J73/J69 -> 0.6929394
A79: Opening Gross Block/Revenue | C79: =C63/IS!C4 -> 0.0041705664 | D79: =D63/IS!D4 -> 0.005730256 | E79: =E63/IS!E4 -> 0.0055562001 | F79: =F63/IS!F4 -> 0.0062056822 | G79: =G63/IS!G4 -> 0.0063382289 | H79: =Assumption!H49 -> 0.0058382289 | I79: =Assumption!I49 -> 0.0053382289 | J79: =Assumption!J49 -> 0.0048382289
A82: Vehicles
A83: Opening Gross Block | C83: 296.74 | D83: 443.03 | E83: 921.96 | F83: 892.97 | G83: 1240.1 | H83: =G86 -> 1763.6212 | I83: =H86 -> 2287.1425 | J83: =I86 -> 2810.6637
A84: Add:Capex | C84: 202.03 | D84: 608.91 | E84: 1136.17 | F84: 742.09 | G84: =G99*'Revenue Model'!G13 -> 523.52125 | H84: =H99*'Revenue Model'!H13 -> 523.52125 | I84: =I99*'Revenue Model'!I13 -> 523.52125 | J84: =J99*'Revenue Model'!J13 -> 1308.8031
A85: Less:Disposal/Sale | C85: -55.74 | D85: -129.98 | E85: -1165.16 | F85: -394.96 | G85: 0 | H85: 0 | I85: 0 | J85: 0
A86: Closing Gross Block | C86: 443.03 | D86: 921.96 | E86: 892.97 | F86: 1240.1 | G86: =G83+G84+G85 -> 1763.6212 | H86: =H83+H84+H85 -> 2287.1425 | I86: =I83+I84+I85 -> 2810.6637 | J86: =J83+J84+J85 -> 4119.4669
A88: Opening Accumulated Depreciation | C88: 97.94 | D88: 116.61 | E88: 148.26 | F88: 118.7 | G88: 163.22 | H88: =G91 -> 287.23 | I88: =H91 -> 463.59212 | J88: =I91 -> 692.30637
A89: Depreciation for the year | C89: 43.43 | D89: 80.99 | E89: 126 | F89: 120.86 | G89: =G83/G95 -> 124.01 | H89: =H83/H95 -> 176.36212 | I89: =I83/I95 -> 228.71425 | J89: =J83/J95 -> 281.06637
A90: Accumulated depreciation on disposals | C90: -24.76 | D90: -49.34 | E90: -155.56 | F90: -76.34 | G90: 0 | H90: 0 | I90: 0 | J90: 0
A91: Ending Accumulated Depreciation | C91: 116.61 | D91: 148.26 | E91: 118.7 | F91: 163.22 | G91: =G88+G89+G90 -> 287.23 | H91: =H88+H89+H90 -> 463.59212 | I91: =I88+I89+I90 -> 692.30637 | J91: =J88+J89+J90 -> 973.37275
A93: Closing Net Block | C93: 326.42 | D93: 773.7 | E93: 774.27 | F93: 1076.88 | G93: =G86-G91 -> 1476.3912 | H93: =H86-H91 -> 1823.5504 | I93: =I86-I91 -> 2118.3574 | J93: =J86-J91 -> 3146.0941
A95: Total Useful Life | B95: Cl.Gross Block/Depri for the year | C95: =C86/C89 -> 10.201013 | D95: =D86/D89 -> 11.383628 | E95: =E86/E89 -> 7.0870635 | F95: =F86/F89 -> 10.260632 | G95: =Assumption!G53 -> 10 | H95: =Assumption!H53 -> 10 | I95: =Assumption!I53 -> 10 | J95: =Assumption!J53 -> 10
A96: Age | B96: Cl.Acc Depri/Depri for the year | C96: =C91/C89 -> 2.6850104 | D96: =D91/D89 -> 1.8305964 | E96: =E91/E89 -> 0.94206349 | F96: =F91/F89 -> 1.3504882 | G96: =G91/G89 -> 2.3161842 | H96: =H91/H89 -> 2.6286377 | I96: =I91/I89 -> 3.026949 | J96: =J91/J89 -> 3.4631419
A97: Remaining Useful Life | B97: Cl.Net Bloc/Depri for the year | C97: =C93/C89 -> 7.5160028 | D97: =D93/D89 -> 9.5530312 | E97: =E93/E89 -> 6.145 | F97: =F93/F89 -> 8.910144 | G97: =G93/G89 -> 11.905421 | H97: =H93/H89 -> 10.339807 | I97: =I93/I89 -> 9.2620262 | J97: =J93/J89 -> 11.19342
A99: Capex/Number of new store | C99: =C84/'Revenue Model'!C13 -> 33.671667 | D99: =D84/'Revenue Model'!D13 -> 86.987143 | E99: =E84/'Revenue Model'!E13 -> 113.617 | F99: =F84/'Revenue Model'!F13 -> 27.484815 | G99: =Assumption!G54 -> 65.440156 | H99: =Assumption!H54 -> 65.440156 | I99: =Assumption!I54 -> 65.440156 | J99: =Assumption!J54 -> 65.440156
A101: Total
A102: Opening Gross Block | C102: 5021.47 | D102: 6176.44 | E102: 8082.36 | F102: 10184.92 | G102: =G6+G25+G42+G63+G83 -> 14592.23 | H102: =H6+H25+H42+H63+H83 -> 16488.859 | I102: =I6+I25+I42+I63+I83 -> 18336.395 | J102: =J6+J25+J42+J63+J83 -> 20221.708
A103: Add:Capex | C103: 1369.16 | D103: 2550.17 | E103: 3459.38 | F103: 5578.46 | G103: =G7+G26+G43+G64+G84 -> 1896.6287 | H103: =H7+H26+H43+H64+H84 -> 1847.5359 | I103: =I7+I26+I43+I64+I84 -> 1885.3135 | J103: =J7+J26+J43+J64+J84 -> 4402.7954
A104: Less:Disposal/Sale | C104: -214.19 | D104: -644.25 | E104: -1337.63 | F104: -1171.15 | G104: =G8+G27+G44+G65+G85 -> 0 | H104: =H8+H27+H44+H65+H85 -> 0 | I104: =I8+I27+I44+I65+I85 -> 0 | J104: =J8+J27+J44+J65+J85 -> 0
A105: Deletion on account of deemed disposal of Subsidiary | C105: - | D105: - | E105: -19.19 | F105: -
A106: Closing Gross Block | C106: 6176.44 | D106: 8082.36 | E106: 10184.92 | F106: 14592.23 | G106: =G9+G28+G46+G66+G86 -> 16488.859 | H106: =H9+H28+H46+H66+H86 -> 18336.395 | I106: =I9+I28+I46+I66+I86 -> 20221.708 | J106: =J9+J28+J46+J66+J86 -> 24624.503
A108: Opening Accumulated Depreciation | C108: 1953.15 | D108: 2450.42 | E108: 2797.95 | F108: 3860.73 | G108: =G11+G30+G48+G68+G88 -> 4815.52 | H108: =H11+H30+H48+H68+H88 -> 6625.0053 | I108: =I11+I30+I48+I68+I88 -> 8671.4756 | J108: =J11+J30+J48+J68+J88 -> 10945.112
A109: Depreciation for the year | C109: 673.37 | D109: 895.67 | E109: 1363.53 | F109: 1755.67 | G109: =G12+G31+G49+G69+G89 -> 1809.4853 | H109: =H12+H31+H49+H69+H89 -> 2046.4703 | I109: =I12+I31+I49+I69+I89 -> 2273.6368 | J109: =J12+J31+J49+J69+J89 -> 2508.3588
A110: Accumulated depreciation on disposals | C110: -176.1 | D110: -548.14 | E110: -299.48 | F110: -800.88 | G110: =G13+G32+G50+G70+G90 -> 0 | H110: =H13+H32+H50+H70+H90 -> 0 | I110: =I13+I32+I50+I70+I90 -> 0 | J110: =J13+J32+J50+J70+J90 -> 0
A111: Deletion on account of deemed disposal of Subsidiary | D111: - | E111: -1.27 | F111: -
A112: Ending Accumulated Depreciation | C112: 2450.42 | D112: 2797.95 | E112: 3860.73 | F112: 4815.52 | G112: =G14+G33+G52+G71+G91 -> 6625.0053 | H112: =H14+H33+H52+H71+H91 -> 8671.4756 | I112: =I14+I33+I52+I71+I91 -> 10945.112 | J112: =J14+J33+J52+J71+J91 -> 13453.471
A114: Closing Net Block | C114: 3726.02 | D114: 5284.41 | E114: 6324.19 | F114: 9776.71 | G114: =G16+G35+G54+G73+G93 -> 9863.8534 | H114: =H16+H35+H54+H73+H93 -> 9664.919 | I114: =I16+I35+I54+I73+I93 -> 9276.5957 | J114: =J16+J35+J54+J73+J93 -> 11171.032
A116: Total Useful Life | B116: Cl.Gross Block/Depri for the year | C116: =C106/C109 -> 9.1724312 | D116: =D106/D109 -> 9.0238146 | E116: =E106/E109 -> 7.469524 | F116: =F106/F109 -> 8.3114879 | G116: =G106/G109 -> 9.112458 | H116: =H106/H109 -> 8.96001 | I116: =I106/I109 -> 8.8939922 | J116: =J106/J109 -> 9.8169781
A117: Age | B117: Cl.Acc Depri/Depri for the year | C117: =C112/C109 -> 3.6390395 | D117: =D112/D109 -> 3.1238626 | E117: =E112/E109 -> 2.8314229 | F117: =F112/F109 -> 2.7428389 | G117: =G112/G109 -> 3.6612651 | H117: =H112/H109 -> 4.2372838 | I117: =I112/I109 -> 4.8139229 | J117: =J112/J109 -> 5.3634556
A118: Remaining Useful Life | B118: Cl.Net Bloc/Depri for the year | C118: =C114/C109 -> 5.5333917 | D118: =D114/D109 -> 5.899952 | E118: =E114/E109 -> 4.6381011 | F118: =F114/F109 -> 5.568649 | G118: =G114/G109 -> 5.4511929 | H118: =H114/H109 -> 4.7227262 | I118: =I114/I109 -> 4.0800693 | J118: =J114/J109 -> 4.4535224
A120: Capital Work-in-progress
A121: Opening Gross Block | C121: 375.73 | D121: 0 | E121: 401.45 | F121: 701.79 | G121: 3057.41 | H121: =G124 -> 3057.41 | I121: =H124 -> 3057.41 | J121: =I124 -> 3057.41
A122: Add:Capex | C122: 590.43 | D122: 401.45 | E122: 1071.86 | F122: 6784.91 | G122: 0 | H122: 0 | I122: 0 | J122: 0
A123: Less:Disposal/Sale | C123: -966.16 | D123: 0 | E123: -771.52 | F123: -4429.29 | G123: 0 | H123: 0 | I123: 0 | J123: 0
A124: Closing Gross Block | C124: 0 | D124: 401.45 | E124: 701.79 | F124: 3057.41 | G124: =G121+G122+G123 -> 3057.41 | H124: =H121+H122+H123 -> 3057.41 | I124: =I121+I122+I123 -> 3057.41 | J124: =J121+J122+J123 -> 3057.41

Sheet WC Schedule
A1: Working Capital Schedule
A2: Figures in lakhs
A3: Particular/Years | B3: Comments | C3: 2021-22 A | D3: 2022-23 A | E3: 2023-24 A | F3: 2024-25 A | G3: 2025-26 E | H3: 2026-27 E | I3: 2027-28 E | J3: 2028-29 E
A4: =IS!A4 -> Revenue from operations | C4: =IS!C4 -> 57728.37 | D4: =IS!D4 -> 78853.37 | E4: =IS!E4 -> 99899.21 | F4: =IS!F4 -> 125162.71 | G4: =IS!G4 -> 185499.77 | H4: =IS!H4 -> 238779.17 | I4: =IS!I4 -> 292842.84 | J4: =IS!J4 -> 365888.92
A5: =IS!A5 -> Cost of Goods Sold | C5: =IS!C5 -> 41112.44 | D5: =IS!D5 -> 54438.49 | E5: =IS!E5 -> 69836.05 | F5: =IS!F5 -> 87667.73 | G5: =IS!G5 -> 127994.84 | H5: =IS!H5 -> 171921 | I5: =IS!I5 -> 204989.99 | J5: =IS!J5 -> 256122.25
A7: Inventory
A8: =BS!A20 -> Inventories | C8: =BS!C20 -> 24993.29 | D8: =BS!D20 -> 33987.29 | E8: =BS!E20 -> 43969.18 | F8: =BS!F20 -> 59267.06 | G8: =G5/G9 -> 77147.576 | H8: =H5/H9 -> 94203.29 | I8: =I5/I9 -> 106707.12 | J8: =J5/J9 -> 126306.86
A9: Inventory Turnover Ratio | B9: COGS/Cl. Inventory - No avg. inventory cause it's giving inconsistent number | C9: - | D9: =D5/D8 -> 1.6017308 | E9: =E5/E8 -> 1.5882955 | F9: =F5/F8 -> 1.4791982 | G9: =365/G10 -> 1.6590909 | H9: =365/H10 -> 1.825 | I9: =365/I10 -> 1.9210526 | J9: =365/J10 -> 2.0277778
A10: Number of Days in Inventory | B10: 365/Inventory Turnover Ratio | C10: - | D10: =365/D9 -> 227.87849 | E10: =365/E9 -> 229.80611 | F10: =365/F9 -> 246.7553 | G10: =Assumption!G71 -> 220 | H10: =Assumption!H71 -> 200 | I10: =Assumption!I71 -> 190 | J10: =Assumption!J71 -> 180
A12: Trade Receviable
A13: =BS!A21 -> Trade receivables | C13: =BS!C21 -> 518.26 | D13: =BS!D21 -> 617.74 | E13: =BS!E21 -> 1557.19 | F13: =BS!F21 -> 1825.95 | G13: =G5/G14 -> 1753.354 | H13: =H5/H14 -> 2355.0823 | I13: =I5/I14 -> 2808.0821 | J13: =J5/J14 -> 3508.5239
A14: Trade Receivable Turnover Ratio | B14: Revenue from operations/Cl. Trade Receivables | C14: - | D14: =D4/D13 -> 127.64815 | E14: =E4/E13 -> 64.153514 | F14: =F4/F13 -> 68.546625 | G14: =365/G15 -> 73 | H14: =365/H15 -> 73 | I14: =365/I15 -> 73 | J14: =365/J15 -> 73
A15: Number of Days in Trade Receivable | B15: 365/Average Trade Receivable | C15: - | D15: =365/D14 -> 2.8594225 | E15: =365/E14 -> 5.6894779 | F15: =365/F14 -> 5.3248428 | G15: =Assumption!G72 -> 5 | H15: =Assumption!H72 -> 5 | I15: =Assumption!I72 -> 5 | J15: =Assumption!J72 -> 5
A17: Trade Payable
A18: =BS!A46 -> Trade payables | C18: =BS!C46 -> 8354.08 | D18: =BS!D46 -> 9658.34 | E18: =BS!E46 -> 9596.77 | F18: =BS!F46 -> 8875.75 | G18: =G19/G20 -> 17984.633 | H18: =H19/H20 -> 25887.222 | I18: =I19/I20 -> 32773.041 | J18: =J19/J20 -> 45324.163
A19: Purchases | B19: Closing Inventory +COGS-Opening Inventory | C19: - | D19: =D8+D5-C8 -> 63432.49 | E19: =E8+E5-D8 -> 79817.94 | F19: =F8+F5-E8 -> 102965.61 | G19: =G8+G5-F8 -> 145875.36 | H19: =H8+H5-G8 -> 188976.72 | I19: =I8+I5-H8 -> 217493.82 | J19: =J8+J5-I8 -> 275721.99
A20: Trade Payable Turnover Ratio | B20: Puchases/Cl. Trade Payable | C20: - | D20: =D19/D18 -> 6.567639 | E20: =E19/E18 -> 8.3171671 | F20: =F19/F18 -> 11.600779 | G20: =365/G21 -> 8.1111111 | H20: =365/H21 -> 7.3 | I20: =365/I21 -> 6.6363636 | J20: =365/J21 -> 6.0833333
A21: Number of days of Trade Payable | B21: 365/Trade Payable Turnover Ratio | C21: - | D21: =365/D20 -> 55.575528 | E21: =365/E20 -> 43.885135 | F21: =365/F20 -> 31.463406 | G21: =Assumption!G73 -> 45 | H21: =Assumption!H73 -> 50 | I21: =Assumption!I73 -> 55 | J21: =Assumption!J73 -> 60
G23: =G18-F18 -> 9108.8831 | H23: =H18-G18 -> 7902.5888 | I23: =I18-H18 -> 6885.8193 | J23: =J18-I18 -> 12551.121

Sheet Lease Schedule 
A1: Lease Schedule
A2: Figures in lakhs
A3: Particular/Years | B3: Comments | C3: 2021-22 A | D3: 2022-23 A | E3: 2023-24 A | F3: 2024-25 A | G3: 2025-26 E | H3: 2026-27 E | I3: 2027-28 E | J3: 2028-29 E
A5: Right of use asset
A6: Opening Balance | C6: 8122.03 | D6: 9159.13 | E6: 10345.04 | F6: 12541.03 | G6: =F10 -> 26045.04 | H6: =G10 -> 23933.78 | I6: =H10 -> 22438.335 | J6: =I10 -> 21406.511
A7: Additions | C7: 3715.13 | D7: 3995.74 | E7: 5690.97 | F7: 19951.43 | G7: =G12 -> 4400 | H7: =H12 -> 4488 | I7: =I12 -> 4577.76 | J7: =J12 -> 11673.288
A8: Deletions | C8: -217.87 | D8: -261.4 | E8: -63.49 | F8: -1194.99 | G8: 0 | H8: 0 | I8: 0 | J8: 0
A9: Depreciation expense | C9: 2460.16 | D9: 2548.43 | E9: 3431.49 | F9: 4532.7 | G9: =G6/G17 -> 6511.26 | H9: =H6/H17 -> 5983.445 | I9: =I6/I17 -> 5609.5837 | J9: =J6/J17 -> 5351.6278
A10: Closing Balance | C10: 9159.13 | D10: 10345.04 | E10: 12541.03 | F10: 26045.04 | G10: =G6+G7+G8-G9 -> 23933.78 | H10: =H6+H7+H8-H9 -> 22438.335 | I10: =I6+I7+I8-I9 -> 21406.511 | J10: =J6+J7+J8-J9 -> 27728.171
A12: Net Addition of ROU | C12: =C7+C8 -> 3497.26 | D12: =D7+D8 -> 3734.34 | E12: =E7+E8 -> 5627.48 | F12: =F7+F8 -> 18756.44 | G12: =G13*G15 -> 4400 | H12: =H13*H15 -> 4488 | I12: =I13*I15 -> 4577.76 | J12: =J13*J15 -> 11673.288
A13: ='Revenue Model'!A13 -> Number of Stores Newly opened during the year | C13: ='Revenue Model'!C13 -> 6 | D13: ='Revenue Model'!D13 -> 7 | E13: ='Revenue Model'!E13 -> 10 | F13: ='Revenue Model'!F13 -> 27 | G13: ='Revenue Model'!G13 -> 8 | H13: ='Revenue Model'!H13 -> 8 | I13: ='Revenue Model'!I13 -> 8 | J13: ='Revenue Model'!J13 -> 20
A15: Net Addition to ROU per newly opened store | C15: =C12/C13 -> 582.87667 | D15: =D12/D13 -> 533.47714 | E15: =E12/E13 -> 562.748 | F15: =F12/F13 -> 694.68296 | G15: =Assumption!G59 -> 550 | H15: =Assumption!H59 -> 561 | I15: =Assumption!I59 -> 572.22 | J15: =Assumption!J59 -> 583.6644
A17: Average Remaining life of the lease | B17: On the Opening Balance | C17: =C6/C9 -> 3.3014235 | D17: =D6/D9 -> 3.5940285 | E17: =E6/E9 -> 3.014737 | F17: =F6/F9 -> 2.7667902 | G17: =Assumption!G60 -> 4 | H17: =Assumption!H60 -> 4 | I17: =Assumption!I60 -> 4 | J17: =Assumption!J60 -> 4
A20: Lease Liabilities
A21: Opening Balance | C21: 8819.37 | D21: 10186.97 | E21: 11273.55 | F21: 13831.86 | G21: 28676.09 | H21: =G30 -> 26919.915 | I21: =H30 -> 25628.755 | J21: =I30 -> 24704.541
A22: Additions | C22: 3591.35 | D22: 3774.47 | E22: 5441.3 | F22: 19348.41 | G22: =G12 -> 4400 | H22: =H12 -> 4488 | I22: =I12 -> 4577.76 | J22: =J12 -> 11673.288
A23: Deletions | C23: -214.55 | D23: -285.17 | E23: -68.13 | F23: -1299.03 | G23: 0 | H23: 0 | I23: 0 | J23: 0
A25: Payment | C25: 2225.57 | D25: 3555.63 | E25: 4326.22 | F25: 5765.74 | G25: =PMT(G35,G36,-G21) -> 9095.4741 | H25: =PMT(H35,H36,-H21) -> 8538.4511 | I25: =PMT(I35,I36,-I21) -> 8128.9214 | J25: =PMT(J35,J36,-J21) -> 7835.7795
A26: Payment towards Interest | C26: 1020.83 | D26: 1152.91 | E26: 1511.36 | F26: =1824.71+735.88 -> 2560.59 | G26: =G21*G35 -> 2939.2992 | H26: =H21*H35 -> 2759.2913 | I26: =I21*I35 -> 2626.9474 | J26: =J21*J35 -> 2532.2155
A27: Payment towards Principal | C27: =C25-C26 -> 1204.74 | D27: =D25-D26 -> 2402.72 | E27: =E25-E26 -> 2814.86 | F27: =F25-F26 -> 3205.15 | G27: =G25-G26 -> 6156.1749 | H27: =H25-H26 -> 5779.1598 | I27: =I25-I26 -> 5501.974 | J27: =J25-J26 -> 5303.564
A28: Rent Concession | C28: -804.46
A30: Closing Balance | C30: 10186.97 | D30: 11273.55 | E30: 13831.86 | F30: 28676.09 | G30: =G21+G22-G23-G27 -> 26919.915 | H30: =H21+H22-H23-H27 -> 25628.755 | I30: =I21+I22-I23-I27 -> 24704.541 | J30: =J21+J22-J23-J27 -> 31074.265
A31: Towards Current | C31: 2238.4 | D31: 2356.75 | E31: 2731.21 | F31: 4179.48 | G31: =G30*Assumption!G63 -> 4037.9873 | H31: =H30*Assumption!H63 -> 3844.3133 | I31: =I30*Assumption!I63 -> 3705.6812 | J31: =J30*Assumption!J63 -> 4661.1398
A32: Towards Non-Current | C32: 7948.57 | D32: 8916.8 | E32: 11100.65 | F32: 24496.61 | G32: =G30-G31 -> 22881.928 | H32: =H30-H31 -> 21784.442 | I32: =I30-I31 -> 20998.86 | J32: =J30-J31 -> 26413.126
A34: Net addition to lease | C34: =C22+C23 -> 3376.8 | D34: =D22+D23 -> 3489.3 | E34: =E22+E23 -> 5373.17 | F34: =F22+F23 -> 18049.38 | G34: =G12 -> 4400 | H34: =H12 -> 4488 | I34: =I12 -> 4577.76 | J34: =J12 -> 11673.288
A35: Effective Interest Rate | C35: =C26/C21 -> 0.11574863 | D35: =D26/D21 -> 0.11317497 | E35: =E26/E21 -> 0.13406247 | F35: =F26/F21 -> 0.18512261 | G35: =Assumption!G64 -> 0.1025 | H35: =Assumption!H64 -> 0.1025 | I35: =Assumption!I64 -> 0.1025 | J35: =Assumption!J64 -> 0.1025
A36: Lease Tenor | C36: =NPER(C35,C25,-C21) -> 5.6037064 | D36: =NPER(D35,D25,-D21) -> 3.6555166 | E36: =NPER(E35,E25,-E21) -> 3.4162174 | F36: =NPER(F35,F25,-F21) -> 3.4570952 | G36: =G17 -> 4 | H36: =H17 -> 4 | I36: =I17 -> 4 | J36: =J17 -> 4

Sheet Debt Schedule 
A1: Debt Schedule
A2: Figures in lakhs
A3: Particular/Years | B3: Comments | C3: 2021-22 A | D3: 2022-23 A | E3: 2023-24 A | F3: 2024-25 A | G3: 2025-26 E | H3: 2026-27 E | I3: 2027-28 E | J3: 2028-29 E
A5: Interest Cost
A6: Interest expense on borrowings | C6: 568.23 | D6: 243.14 | E6: 84.24 | F6: 95.66 | G6: =G17*G23 -> 24.011225 | H6: =H17*H23 -> 24.011225 | I6: =I17*I23 -> 24.011225 | J6: =J17*J23 -> 24.011225
A7: Interest on lease liabilities | C7: 1020.83 | D7: 1152.91 | E7: 1511.36 | F7: 1824.71 | G7: ='Lease Schedule '!G26 -> 2939.2992 | H7: ='Lease Schedule '!H26 -> 2759.2913 | I7: ='Lease Schedule '!I26 -> 2626.9474 | J7: ='Lease Schedule '!J26 -> 2532.2155
A8: Interest on delay in deposit of income tax | C8: 22.22 | D8: 8.51 | E8: 3.54 | F8: 6.51 | G8: 0 | H8: 0 | I8: 0 | J8: 0
A9: Other finance charges | B9: Includes, mark to mark (MTM) loss on forward contracts | C9: 0 | D9: 0 | E9: 0 | F9: 13.43 | G9: 0 | H9: 0 | I9: 0 | J9: 0
A10: Other borrowing cost | B10: Includes overdue interest due on Micro Small and Medium Enterprises | C10: 56 | D10: 11.5 | E10: 2.66 | F10: 3.53 | G10: 0 | H10: 0 | I10: 0 | J10: 0
A11: Total Interest Cost | C11: 1667.28 | D11: 1416.06 | E11: 1601.8 | F11: 1943.84 | G11: =SUM(G6:G10) -> 2963.3104 | H11: =SUM(H6:H10) -> 2783.3025 | I11: =SUM(I6:I10) -> 2650.9586 | J11: =SUM(J6:J10) -> 2556.2267
A14: Interest Bearing Liabilities
A15: ="Non Current " & BS!A38 -> Non Current Borrowings | C15: =BS!C38 -> 2764.42 | D15: =BS!D38 -> 711.77 | E15: =BS!E38 -> 205.98 | F15: 12.55 | G15: 12.55 | H15: 12.55 | I15: 12.55 | J15: 12.55
A16: ="Current "&BS!A44 -> Current Borrowings | C16: =BS!C44 -> 3177.81 | D16: =BS!D44 -> 87.25 | E16: =BS!E44 -> 463.87 | F16: 183.46 | G16: 183.46 | H16: 183.46 | I16: 183.46 | J16: 183.46
A17: Total Borrowings | C17: =SUM(C15:C16) -> 5942.23 | D17: =SUM(D15:D16) -> 799.02 | E17: =SUM(E15:E16) -> 669.85 | F17: =SUM(F15:F16) -> 196.01 | G17: =SUM(G15:G16) -> 196.01 | H17: =SUM(H15:H16) -> 196.01 | I17: =SUM(I15:I16) -> 196.01 | J17: =SUM(J15:J16) -> 196.01
A18: ="Non Current " &BS!A39 -> Non Current Lease liabilities | C18: =BS!C39 -> 7948.57 | D18: =BS!D39 -> 8916.8 | E18: =BS!E39 -> 11100.65 | F18: =BS!F39 -> 24496.61 | G18: ='Lease Schedule '!G32 -> 22881.928 | H18: ='Lease Schedule '!H32 -> 21784.442 | I18: ='Lease Schedule '!I32 -> 20998.86 | J18: ='Lease Schedule '!J32 -> 26413.126
A19: ="Current " &BS!A45 -> Current Lease liabilities | C19: =BS!C45 -> 2238.4 | D19: =BS!D45 -> 2356.75 | E19: =BS!E45 -> 2731.21 | F19: =BS!F45 -> 4179.48 | G19: ='Lease Schedule '!G31 -> 4037.9873 | H19: ='Lease Schedule '!H31 -> 3844.3133 | I19: ='Lease Schedule '!I31 -> 3705.6812 | J19: ='Lease Schedule '!J31 -> 4661.1398
A20: Total Lease liability | C20: =SUM(C18:C19) -> 10186.97 | D20: =SUM(D18:D19) -> 11273.55 | E20: =SUM(E18:E19) -> 13831.86 | F20: =SUM(F18:F19) -> 28676.09 | G20: ='Lease Schedule '!G30 -> 26919.915 | H20: ='Lease Schedule '!H30 -> 25628.755 | I20: ='Lease Schedule '!I30 -> 24704.541 | J20: ='Lease Schedule '!J30 -> 31074.265
A21: Total Interest Bearing Liabilities | C21: =C17+C20 -> 16129.2 | D21: =D17+D20 -> 12072.57 | E21: =E17+E20 -> 14501.71 | F21: =F17+F20 -> 28872.1 | G21: =G17+G20 -> 27115.925 | H21: =H17+H20 -> 25824.765 | I21: =I17+I20 -> 24900.551 | J21: =J17+J20 -> 31270.275
A23: Effective Interest Rate on Borrowing | C23: - | D23: =D6/C17 -> 0.040917299 | E23: =E6/D17 -> 0.10542915 | F23: =F6/E17 -> 0.14280809 | G23: =Assumption!G68 -> 0.1225 | H23: =Assumption!H68 -> 0.1225 | I23: =Assumption!I68 -> 0.1225 | J23: =Assumption!J68 -> 0.1225

Sheet Notes
A1: Listed on BSE and NSE in 2022
A2: Revenue stream-
A3: New Luxury Watch retail- tie up from brands , buy from them and sell them through their bouquet store and online
A4: Sell pre owned watch retail - Buy used luxury watch , restore them, certify them and sold with warranty
A5: Watch servicing, repairing and accessories
A6: Luxury jeweller and luggage - | B6: Messika Jewellery
B7: Rimowa luggage - 1st store opened in 2025
A10: Particular/Years | B10: 2022 | C10: 2023 | D10: 2024 | E10: 2025
A11: Average Selling price (In Lakhs) | B11: 1.49 | C11: 1.59 | D11: 1.89 | E11: 2.04
A12: Number of stores- | B12: 50 | C12: 56 | D12: 63 | E12: 73
A13: SSG | C13: 0.3 | D13: 0.16 | E13: 0.174
A14: Digitally assisted sales (In Cr.) | B14: 222.8 | C14: 283.9 | D14: 358.6 | E14: 492
A15: Online Visitors(In Lakhs) | B15: 2277000 | C15: 2364300 | D15: 2140500
A17: Impact of EFTA
A18: Impact of Foreign exchange
A20: In IS there is no "Change in WIP" bcz company doesn't produce any watch they buy from brands (Purchase of stock in trade) and sell to end customers (Change in stock in trade (Negative))
A37: News on city of time dated 26 may 2025 | B37: Ethos Watches has unveiled—City of Time, a 22,000-square-foot horological haven in the heart of Gurugram
A44: Concall May 2025- | B44: pg2-The City of Time Gurgaon spanning over 22,000 square feet features five exclusive brand boutiques and two multi-brand galleries with 50-plus independent brands, watchmaking zones, a cigar lounge and more
B45: pg3-Looking ahead, we remain on track to be able to cross 100 boutiques during the current financial year.
B46: Furthermore, inventory for the 8 boutiques opening in May 2025 was proactively prearranged in quarter four to ensure timely and seamless launches. Because of the above reasons, the inventory moved from INR 440 crores on 31st March 2024 to INR593 crores as on 31st March 2025
B47: As part of our international expansion strategy, we have established a wholly-owned subsidiary in the UAE. It's called Ficus Trading LLC.
B48: We have now implemented a prudent hedging strategy covering approximately 50% of our foreign currency exposure through forward contracts
B49: pg8- and in terms of overall volume, it grew by almost 15.5% year-on-year. And in terms of average selling price, it grew by 7.4%.
B50: And as I had mentioned two years ago when the listing was taking place that we want to grow 10x in 10 years has been our vision, right, especially in the retail of watches and premium products in India
B51: Pg12-we see that about a little bit above 40% is repeat buying
B52: Pg13-In addition, there were some brand debit notes. Generally, we get every quarter or half yearly basis. This year, it was accumulated and padded up to the year-end. So that's why you see the reduction in the creditors.
B53: pg16- Manish Poddar: So just two questions. So one is in terms of any sense of our market share in India? How would that be stacking? Pranav Saboo: In the segments that we operate with, we believe that it is about 35% to 40%.
A59: Concall Nov 2024- | B59: pg7-But is there an opportunity in the next 5 years to open 20 stores a year
B60: Pg 8 - In terms of EFTA, the EFTA is a groundbreaking agreement. It will reduce customs duty and it will impact our bottom line in a positive manner.
B61: pg 9- In my opinion over the next 5 years, we are going to at least target an 8X to 10X increase in the business of just Rimowa itself. we hope to open 8 to 10 boutiques more of Messika in the next 5 years.
B62: pg12- As I mentioned our SSG has been 15.5% in the last 6 months. Our goal is to increase our overall revenue, and our overall business will be 10times in 10 years. I think it will be a healthy mix of same store growth and new store addition
A65: Concall May 2023 | B65: pg7-SSG numbers, for the year, for the last year, the SSG was 30%. So which is extremely strong. Our overall target, our steady target for, the next three to four years is an SSG target between 12% and 15%. So last year, of course, was completely an outlier.But 12% to 15% SSG growth is our target, a long-term target.

Sheet Template 
A1: Sheet Name
A2: Figures in lakhs
A3: Particular/Years | B3: Comments | C3: 2021-22 A | D3: 2022-23 A | E3: 2023-24 A | F3: 2024-25 A | G3: 2025-26 E | H3: 2026-27 E | I3: 2027-28 E | J3: 2028-29 E
